[{"_path":"/comments/1645108582029_f9c0a5a0-8ffe-11ec-8cbb-91b153d121e6","_dir":"comments","_draft":false,"_partial":false,"_locale":"","_id":"content:comments:1645108582029_f9c0a5a0-8ffe-11ec-8cbb-91b153d121e6.yml","message":"manque d'exos vraiment !","level":"premiere","lesson":"fonctions-trigonometriques","author":"Anonyme","client":"Android","date":1645108582,"_type":"yaml","title":"1645108582029F9c0a5a0 8ffe 11ec 8cbb 91b153d121e6","_source":"content","_file":"comments/1645108582029_f9c0a5a0-8ffe-11ec-8cbb-91b153d121e6.yml","_extension":"yml"},{"_path":"/comments/1644145749266_34b36690-873d-11ec-8162-4b073e953ce3","_dir":"comments","_draft":false,"_partial":false,"_locale":"","_id":"content:comments:1644145749266_34b36690-873d-11ec-8162-4b073e953ce3.yml","lesson":"fonctions-trigonometriques","level":"premiere","client":"bacomathiqu.es","message":"Oui.cours precis","author":"Abdelkader Gourama","date":1644145749,"_type":"yaml","title":"164414574926634b36690 873d 11ec 8162 4b073e953ce3","_source":"content","_file":"comments/1644145749266_34b36690-873d-11ec-8162-4b073e953ce3.yml","_extension":"yml"},{"_path":"/comments/1601933247060_90cc8500-0751-11eb-b15c-d7e1c16a6f5e","_dir":"comments","_draft":false,"_partial":false,"_locale":"","_id":"content:comments:1601933247060_90cc8500-0751-11eb-b15c-d7e1c16a6f5e.yml","lesson":"fonctions-trigonometriques","level":"premiere","client":"bacomathiqu.es","message":"C'est en projet, mais je dois d'abord terminer de rédiger les cours de Maths expertes (pour les Terminales Spé Maths) avant. Je suis seul pour maintenir le site et y ajouter du contenu (et le tenir à jour), et je le fais sur mon temps libre, donc il faudra patienter encore un peu 😉","author":"Skyost","date":1601933247,"_type":"yaml","title":"160193324706090cc8500 0751 11eb B15c D7e1c16a6f5e","_source":"content","_file":"comments/1601933247060_90cc8500-0751-11eb-b15c-d7e1c16a6f5e.yml","_extension":"yml"},{"_path":"/comments/1601932783323_7c5b52f0-0750-11eb-b15c-d7e1c16a6f5e","_dir":"comments","_draft":false,"_partial":false,"_locale":"","_id":"content:comments:1601932783323_7c5b52f0-0750-11eb-b15c-d7e1c16a6f5e.yml","message":"mais normalement vous devez donner des exemples  d'exercices  pour qu'on puisse bien comprendre","level":"premiere","lesson":"fonctions-trigonometriques","author":"Anonyme","client":"Android","date":1601932783,"_type":"yaml","title":"16019327833237c5b52f0 0750 11eb B15c D7e1c16a6f5e","_source":"content","_file":"comments/1601932783323_7c5b52f0-0750-11eb-b15c-d7e1c16a6f5e.yml","_extension":"yml"}]