{"_path":"/latex/lessons/terminale/variables-aleatoires-concentration-grands-nombres","_dir":"terminale","_draft":false,"_partial":false,"_locale":"","_id":"content:latex:lessons:terminale:variables-aleatoires-concentration-grands-nombres.tex","summary":"\n\n\n\n\n\n\n\n<h2 id=\"somme-de-deux-variables-aleatoires\">Somme de deux variables aléatoires</h2>\n<h3 id=\"definition\">Définition</h3>\n<p>Il arrive que, on ne puisse pas modéliser une situation donnée à\nl’aide d’une seule variable aléatoire <q>simple</q>. C’est pourquoi il\nest parfois utile d’en additionner plusieurs ou bien d’en multiplier par\nun réel.</p>\n<div id=\"formula-1\" class=\"bubble\" data-variant=\"formula\">\n<h4>Définition</h4>\n<p>Soient <span class=\"math-rendered\" data-latex=\"X\" data-latex-display=\"false\"><span class=\"katex\"><span class=\"katex-html\" aria-hidden=\"true\"><span class=\"base\"><span class=\"strut\" style=\"height:0.6833em;\"></span><span class=\"mord mathnormal\" style=\"margin-right:0.07847em;\">X</span></span></span></span></span> et <span class=\"math-rendered\" data-latex=\"Y\" data-latex-display=\"false\"><span class=\"katex\"><span class=\"katex-html\" aria-hidden=\"true\"><span class=\"base\"><span class=\"strut\" style=\"height:0.6833em;\"></span><span class=\"mord mathnormal\" style=\"margin-right:0.22222em;\">Y</span></span></span></span></span> deux variables\naléatoires définies sur un univers <span class=\"math-rendered\" data-latex=\"\\Omega\" data-latex-display=\"false\"><span class=\"katex\"><span class=\"katex-html\" aria-hidden=\"true\"><span class=\"base\"><span class=\"strut\" style=\"height:0.6833em;\"></span><span class=\"mord\">Ω</span></span></span></span></span> et soit\n<span class=\"math-rendered\" data-latex=\"\\lambda\" data-latex-display=\"false\"><span class=\"katex\"><span class=\"katex-html\" aria-hidden=\"true\"><span class=\"base\"><span class=\"strut\" style=\"height:0.6944em;\"></span><span class=\"mord mathnormal\">λ</span></span></span></span></span> un réel. On définit :</p>\n<ul>\n<li><p><span class=\"math-rendered\" data-latex=\"X + Y\" data-latex-display=\"false\"><span class=\"katex\"><span class=\"katex-html\" aria-hidden=\"true\"><span class=\"base\"><span class=\"strut\" style=\"height:0.7667em;vertical-align:-0.0833em;\"></span><span class=\"mord mathnormal\" style=\"margin-right:0.07847em;\">X</span><span class=\"mspace\" style=\"margin-right:0.2222em;\"></span><span class=\"mbin\">+</span><span class=\"mspace\" style=\"margin-right:0.2222em;\"></span></span><span class=\"base\"><span class=\"strut\" style=\"height:0.6833em;\"></span><span class=\"mord mathnormal\" style=\"margin-right:0.22222em;\">Y</span></span></span></span></span> la variable aléatoire somme de <span class=\"math-rendered\" data-latex=\"X\" data-latex-display=\"false\"><span class=\"katex\"><span class=\"katex-html\" aria-hidden=\"true\"><span class=\"base\"><span class=\"strut\" style=\"height:0.6833em;\"></span><span class=\"mord mathnormal\" style=\"margin-right:0.07847em;\">X</span></span></span></span></span> et <span class=\"math-rendered\" data-latex=\"Y\" data-latex-display=\"false\"><span class=\"katex\"><span class=\"katex-html\" aria-hidden=\"true\"><span class=\"base\"><span class=\"strut\" style=\"height:0.6833em;\"></span><span class=\"mord mathnormal\" style=\"margin-right:0.22222em;\">Y</span></span></span></span></span> définie pour tout <span class=\"math-rendered\" data-latex=\"\\omega \\in \\Omega\" data-latex-display=\"false\"><span class=\"katex\"><span class=\"katex-html\" aria-hidden=\"true\"><span class=\"base\"><span class=\"strut\" style=\"height:0.5782em;vertical-align:-0.0391em;\"></span><span class=\"mord mathnormal\" style=\"margin-right:0.03588em;\">ω</span><span class=\"mspace\" style=\"margin-right:0.2778em;\"></span><span class=\"mrel\">∈</span><span class=\"mspace\" style=\"margin-right:0.2778em;\"></span></span><span class=\"base\"><span class=\"strut\" style=\"height:0.6833em;\"></span><span class=\"mord\">Ω</span></span></span></span></span> par <span class=\"math-rendered\" data-latex=\"(X + Y)(\\omega) = X(\\omega) + Y(\\omega)\" data-latex-display=\"false\"><span class=\"katex\"><span class=\"katex-html\" aria-hidden=\"true\"><span class=\"base\"><span class=\"strut\" style=\"height:1em;vertical-align:-0.25em;\"></span><span class=\"mopen\">(</span><span class=\"mord mathnormal\" style=\"margin-right:0.07847em;\">X</span><span class=\"mspace\" style=\"margin-right:0.2222em;\"></span><span class=\"mbin\">+</span><span class=\"mspace\" style=\"margin-right:0.2222em;\"></span></span><span class=\"base\"><span class=\"strut\" style=\"height:1em;vertical-align:-0.25em;\"></span><span class=\"mord mathnormal\" style=\"margin-right:0.22222em;\">Y</span><span class=\"mclose\">)</span><span class=\"mopen\">(</span><span class=\"mord mathnormal\" style=\"margin-right:0.03588em;\">ω</span><span class=\"mclose\">)</span><span class=\"mspace\" style=\"margin-right:0.2778em;\"></span><span class=\"mrel\">=</span><span class=\"mspace\" style=\"margin-right:0.2778em;\"></span></span><span class=\"base\"><span class=\"strut\" style=\"height:1em;vertical-align:-0.25em;\"></span><span class=\"mord mathnormal\" style=\"margin-right:0.07847em;\">X</span><span class=\"mopen\">(</span><span class=\"mord mathnormal\" style=\"margin-right:0.03588em;\">ω</span><span class=\"mclose\">)</span><span class=\"mspace\" style=\"margin-right:0.2222em;\"></span><span class=\"mbin\">+</span><span class=\"mspace\" style=\"margin-right:0.2222em;\"></span></span><span class=\"base\"><span class=\"strut\" style=\"height:1em;vertical-align:-0.25em;\"></span><span class=\"mord mathnormal\" style=\"margin-right:0.22222em;\">Y</span><span class=\"mopen\">(</span><span class=\"mord mathnormal\" style=\"margin-right:0.03588em;\">ω</span><span class=\"mclose\">)</span></span></span></span></span>.</p></li>\n<li><p><span class=\"math-rendered\" data-latex=\"\\lambda X\" data-latex-display=\"false\"><span class=\"katex\"><span class=\"katex-html\" aria-hidden=\"true\"><span class=\"base\"><span class=\"strut\" style=\"height:0.6944em;\"></span><span class=\"mord mathnormal\">λ</span><span class=\"mord mathnormal\" style=\"margin-right:0.07847em;\">X</span></span></span></span></span> la variable aléatoire produit de\n<span class=\"math-rendered\" data-latex=\"\\lambda\" data-latex-display=\"false\"><span class=\"katex\"><span class=\"katex-html\" aria-hidden=\"true\"><span class=\"base\"><span class=\"strut\" style=\"height:0.6944em;\"></span><span class=\"mord mathnormal\">λ</span></span></span></span></span> et <span class=\"math-rendered\" data-latex=\"X\" data-latex-display=\"false\"><span class=\"katex\"><span class=\"katex-html\" aria-hidden=\"true\"><span class=\"base\"><span class=\"strut\" style=\"height:0.6833em;\"></span><span class=\"mord mathnormal\" style=\"margin-right:0.07847em;\">X</span></span></span></span></span> définie pour tout\n<span class=\"math-rendered\" data-latex=\"\\omega \\in \\Omega\" data-latex-display=\"false\"><span class=\"katex\"><span class=\"katex-html\" aria-hidden=\"true\"><span class=\"base\"><span class=\"strut\" style=\"height:0.5782em;vertical-align:-0.0391em;\"></span><span class=\"mord mathnormal\" style=\"margin-right:0.03588em;\">ω</span><span class=\"mspace\" style=\"margin-right:0.2778em;\"></span><span class=\"mrel\">∈</span><span class=\"mspace\" style=\"margin-right:0.2778em;\"></span></span><span class=\"base\"><span class=\"strut\" style=\"height:0.6833em;\"></span><span class=\"mord\">Ω</span></span></span></span></span> par <span class=\"math-rendered\" data-latex=\"(\\lambda X)(\\omega) = \\lambda X(\\omega)\" data-latex-display=\"false\"><span class=\"katex\"><span class=\"katex-html\" aria-hidden=\"true\"><span class=\"base\"><span class=\"strut\" style=\"height:1em;vertical-align:-0.25em;\"></span><span class=\"mopen\">(</span><span class=\"mord mathnormal\">λ</span><span class=\"mord mathnormal\" style=\"margin-right:0.07847em;\">X</span><span class=\"mclose\">)</span><span class=\"mopen\">(</span><span class=\"mord mathnormal\" style=\"margin-right:0.03588em;\">ω</span><span class=\"mclose\">)</span><span class=\"mspace\" style=\"margin-right:0.2778em;\"></span><span class=\"mrel\">=</span><span class=\"mspace\" style=\"margin-right:0.2778em;\"></span></span><span class=\"base\"><span class=\"strut\" style=\"height:1em;vertical-align:-0.25em;\"></span><span class=\"mord mathnormal\">λ</span><span class=\"mord mathnormal\" style=\"margin-right:0.07847em;\">X</span><span class=\"mopen\">(</span><span class=\"mord mathnormal\" style=\"margin-right:0.03588em;\">ω</span><span class=\"mclose\">)</span></span></span></span></span>.</p></li>\n</ul>\n</div>\n\n<h3 id=\"esperance-variance-et-ecart-type\">Espérance, variance et écart-type</h3>\n<p>Une somme de variable aléatoire reste une variable aléatoire. Donc il\nest tout à fait possible de calculer l’espérance, la variance,\nl’écart-type, ... d’une somme de variables aléatoires.</p>\n<p>Voyons dans un premier temps une propriété de l’espérance permettant\nde calculer plus facilement l’espérance d’une combinaison linéaire de\nvariables aléatoires.</p>\n<div id=\"formula-2\" class=\"bubble\" data-variant=\"formula\">\n<h4>Linéarité de l’espérance</h4>\n<p>Soient <span class=\"math-rendered\" data-latex=\"X\" data-latex-display=\"false\"><span class=\"katex\"><span class=\"katex-html\" aria-hidden=\"true\"><span class=\"base\"><span class=\"strut\" style=\"height:0.6833em;\"></span><span class=\"mord mathnormal\" style=\"margin-right:0.07847em;\">X</span></span></span></span></span> et <span class=\"math-rendered\" data-latex=\"Y\" data-latex-display=\"false\"><span class=\"katex\"><span class=\"katex-html\" aria-hidden=\"true\"><span class=\"base\"><span class=\"strut\" style=\"height:0.6833em;\"></span><span class=\"mord mathnormal\" style=\"margin-right:0.22222em;\">Y</span></span></span></span></span> deux variables\naléatoires définies sur un univers <span class=\"math-rendered\" data-latex=\"\\Omega\" data-latex-display=\"false\"><span class=\"katex\"><span class=\"katex-html\" aria-hidden=\"true\"><span class=\"base\"><span class=\"strut\" style=\"height:0.6833em;\"></span><span class=\"mord\">Ω</span></span></span></span></span> et soit\n<span class=\"math-rendered\" data-latex=\"\\lambda\" data-latex-display=\"false\"><span class=\"katex\"><span class=\"katex-html\" aria-hidden=\"true\"><span class=\"base\"><span class=\"strut\" style=\"height:0.6944em;\"></span><span class=\"mord mathnormal\">λ</span></span></span></span></span> un réel. Alors :</p>\n<ul>\n<li><p><span class=\"math-rendered\" data-latex=\"E(X + Y) = E(X) + E(Y)\" data-latex-display=\"false\"><span class=\"katex\"><span class=\"katex-html\" aria-hidden=\"true\"><span class=\"base\"><span class=\"strut\" style=\"height:1em;vertical-align:-0.25em;\"></span><span class=\"mord mathnormal\" style=\"margin-right:0.05764em;\">E</span><span class=\"mopen\">(</span><span class=\"mord mathnormal\" style=\"margin-right:0.07847em;\">X</span><span class=\"mspace\" style=\"margin-right:0.2222em;\"></span><span class=\"mbin\">+</span><span class=\"mspace\" style=\"margin-right:0.2222em;\"></span></span><span class=\"base\"><span class=\"strut\" style=\"height:1em;vertical-align:-0.25em;\"></span><span class=\"mord mathnormal\" style=\"margin-right:0.22222em;\">Y</span><span class=\"mclose\">)</span><span class=\"mspace\" style=\"margin-right:0.2778em;\"></span><span class=\"mrel\">=</span><span class=\"mspace\" style=\"margin-right:0.2778em;\"></span></span><span class=\"base\"><span class=\"strut\" style=\"height:1em;vertical-align:-0.25em;\"></span><span class=\"mord mathnormal\" style=\"margin-right:0.05764em;\">E</span><span class=\"mopen\">(</span><span class=\"mord mathnormal\" style=\"margin-right:0.07847em;\">X</span><span class=\"mclose\">)</span><span class=\"mspace\" style=\"margin-right:0.2222em;\"></span><span class=\"mbin\">+</span><span class=\"mspace\" style=\"margin-right:0.2222em;\"></span></span><span class=\"base\"><span class=\"strut\" style=\"height:1em;vertical-align:-0.25em;\"></span><span class=\"mord mathnormal\" style=\"margin-right:0.05764em;\">E</span><span class=\"mopen\">(</span><span class=\"mord mathnormal\" style=\"margin-right:0.22222em;\">Y</span><span class=\"mclose\">)</span></span></span></span></span>.</p></li>\n<li><p><span class=\"math-rendered\" data-latex=\"E(\\lambda X) = \\lambda E(X)\" data-latex-display=\"false\"><span class=\"katex\"><span class=\"katex-html\" aria-hidden=\"true\"><span class=\"base\"><span class=\"strut\" style=\"height:1em;vertical-align:-0.25em;\"></span><span class=\"mord mathnormal\" style=\"margin-right:0.05764em;\">E</span><span class=\"mopen\">(</span><span class=\"mord mathnormal\">λ</span><span class=\"mord mathnormal\" style=\"margin-right:0.07847em;\">X</span><span class=\"mclose\">)</span><span class=\"mspace\" style=\"margin-right:0.2778em;\"></span><span class=\"mrel\">=</span><span class=\"mspace\" style=\"margin-right:0.2778em;\"></span></span><span class=\"base\"><span class=\"strut\" style=\"height:1em;vertical-align:-0.25em;\"></span><span class=\"mord mathnormal\">λ</span><span class=\"mord mathnormal\" style=\"margin-right:0.05764em;\">E</span><span class=\"mopen\">(</span><span class=\"mord mathnormal\" style=\"margin-right:0.07847em;\">X</span><span class=\"mclose\">)</span></span></span></span></span>.</p></li>\n</ul>\n</div>\n\n<p>Voyons désormais des formules permettant de calculer la variance et\nl’écart-type d’une combinaison linéaire de variables aléatoires.</p>\n<div id=\"formula-3\" class=\"bubble\" data-variant=\"formula\">\n<h4>Variance et écart-type</h4>\n<p>Soient <span class=\"math-rendered\" data-latex=\"X\" data-latex-display=\"false\"><span class=\"katex\"><span class=\"katex-html\" aria-hidden=\"true\"><span class=\"base\"><span class=\"strut\" style=\"height:0.6833em;\"></span><span class=\"mord mathnormal\" style=\"margin-right:0.07847em;\">X</span></span></span></span></span> et <span class=\"math-rendered\" data-latex=\"Y\" data-latex-display=\"false\"><span class=\"katex\"><span class=\"katex-html\" aria-hidden=\"true\"><span class=\"base\"><span class=\"strut\" style=\"height:0.6833em;\"></span><span class=\"mord mathnormal\" style=\"margin-right:0.22222em;\">Y</span></span></span></span></span> deux variables\naléatoires définies sur un univers <span class=\"math-rendered\" data-latex=\"\\Omega\" data-latex-display=\"false\"><span class=\"katex\"><span class=\"katex-html\" aria-hidden=\"true\"><span class=\"base\"><span class=\"strut\" style=\"height:0.6833em;\"></span><span class=\"mord\">Ω</span></span></span></span></span> et soit\n<span class=\"math-rendered\" data-latex=\"\\lambda\" data-latex-display=\"false\"><span class=\"katex\"><span class=\"katex-html\" aria-hidden=\"true\"><span class=\"base\"><span class=\"strut\" style=\"height:0.6944em;\"></span><span class=\"mord mathnormal\">λ</span></span></span></span></span> un réel. Alors :</p>\n<ul>\n<li><p><span class=\"math-rendered\" data-latex=\"V(X + Y) = V(X) + V(Y)\" data-latex-display=\"false\"><span class=\"katex\"><span class=\"katex-html\" aria-hidden=\"true\"><span class=\"base\"><span class=\"strut\" style=\"height:1em;vertical-align:-0.25em;\"></span><span class=\"mord mathnormal\" style=\"margin-right:0.22222em;\">V</span><span class=\"mopen\">(</span><span class=\"mord mathnormal\" style=\"margin-right:0.07847em;\">X</span><span class=\"mspace\" style=\"margin-right:0.2222em;\"></span><span class=\"mbin\">+</span><span class=\"mspace\" style=\"margin-right:0.2222em;\"></span></span><span class=\"base\"><span class=\"strut\" style=\"height:1em;vertical-align:-0.25em;\"></span><span class=\"mord mathnormal\" style=\"margin-right:0.22222em;\">Y</span><span class=\"mclose\">)</span><span class=\"mspace\" style=\"margin-right:0.2778em;\"></span><span class=\"mrel\">=</span><span class=\"mspace\" style=\"margin-right:0.2778em;\"></span></span><span class=\"base\"><span class=\"strut\" style=\"height:1em;vertical-align:-0.25em;\"></span><span class=\"mord mathnormal\" style=\"margin-right:0.22222em;\">V</span><span class=\"mopen\">(</span><span class=\"mord mathnormal\" style=\"margin-right:0.07847em;\">X</span><span class=\"mclose\">)</span><span class=\"mspace\" style=\"margin-right:0.2222em;\"></span><span class=\"mbin\">+</span><span class=\"mspace\" style=\"margin-right:0.2222em;\"></span></span><span class=\"base\"><span class=\"strut\" style=\"height:1em;vertical-align:-0.25em;\"></span><span class=\"mord mathnormal\" style=\"margin-right:0.22222em;\">V</span><span class=\"mopen\">(</span><span class=\"mord mathnormal\" style=\"margin-right:0.22222em;\">Y</span><span class=\"mclose\">)</span></span></span></span></span> si <span class=\"math-rendered\" data-latex=\"X\" data-latex-display=\"false\"><span class=\"katex\"><span class=\"katex-html\" aria-hidden=\"true\"><span class=\"base\"><span class=\"strut\" style=\"height:0.6833em;\"></span><span class=\"mord mathnormal\" style=\"margin-right:0.07847em;\">X</span></span></span></span></span> et <span class=\"math-rendered\" data-latex=\"Y\" data-latex-display=\"false\"><span class=\"katex\"><span class=\"katex-html\" aria-hidden=\"true\"><span class=\"base\"><span class=\"strut\" style=\"height:0.6833em;\"></span><span class=\"mord mathnormal\" style=\"margin-right:0.22222em;\">Y</span></span></span></span></span> sont indépendantes\n(c’est-à-dire si le résultat de l’une n’a pas d’incidence sur le\nrésultat de l’autre).</p></li>\n<li><p><span class=\"math-rendered\" data-latex=\"V(\\lambda X) = \\lambda^2 V(X)\" data-latex-display=\"false\"><span class=\"katex\"><span class=\"katex-html\" aria-hidden=\"true\"><span class=\"base\"><span class=\"strut\" style=\"height:1em;vertical-align:-0.25em;\"></span><span class=\"mord mathnormal\" style=\"margin-right:0.22222em;\">V</span><span class=\"mopen\">(</span><span class=\"mord mathnormal\">λ</span><span class=\"mord mathnormal\" style=\"margin-right:0.07847em;\">X</span><span class=\"mclose\">)</span><span class=\"mspace\" style=\"margin-right:0.2778em;\"></span><span class=\"mrel\">=</span><span class=\"mspace\" style=\"margin-right:0.2778em;\"></span></span><span class=\"base\"><span class=\"strut\" style=\"height:1.0641em;vertical-align:-0.25em;\"></span><span class=\"mord\"><span class=\"mord mathnormal\">λ</span><span class=\"msupsub\"><span class=\"vlist-t\"><span class=\"vlist-r\"><span class=\"vlist\" style=\"height:0.8141em;\"><span style=\"top:-3.063em;margin-right:0.05em;\"><span class=\"pstrut\" style=\"height:2.7em;\"></span><span class=\"sizing reset-size6 size3 mtight\"><span class=\"mord mtight\">2</span></span></span></span></span></span></span></span><span class=\"mord mathnormal\" style=\"margin-right:0.22222em;\">V</span><span class=\"mopen\">(</span><span class=\"mord mathnormal\" style=\"margin-right:0.07847em;\">X</span><span class=\"mclose\">)</span></span></span></span></span>.</p></li>\n<li><p><span class=\"math-rendered\" data-latex=\"\\sigma(\\lambda X) = \\sqrt{\\lambda^2} \\sigma(X)\" data-latex-display=\"false\"><span class=\"katex\"><span class=\"katex-html\" aria-hidden=\"true\"><span class=\"base\"><span class=\"strut\" style=\"height:1em;vertical-align:-0.25em;\"></span><span class=\"mord mathnormal\" style=\"margin-right:0.03588em;\">σ</span><span class=\"mopen\">(</span><span class=\"mord mathnormal\">λ</span><span class=\"mord mathnormal\" style=\"margin-right:0.07847em;\">X</span><span class=\"mclose\">)</span><span class=\"mspace\" style=\"margin-right:0.2778em;\"></span><span class=\"mrel\">=</span><span class=\"mspace\" style=\"margin-right:0.2778em;\"></span></span><span class=\"base\"><span class=\"strut\" style=\"height:1.2051em;vertical-align:-0.25em;\"></span><span class=\"mord sqrt\"><span class=\"vlist-t vlist-t2\"><span class=\"vlist-r\"><span class=\"vlist\" style=\"height:0.9551em;\"><span class=\"svg-align\" style=\"top:-3em;\"><span class=\"pstrut\" style=\"height:3em;\"></span><span class=\"mord\" style=\"padding-left:0.833em;\"><span class=\"mord\"><span class=\"mord mathnormal\">λ</span><span class=\"msupsub\"><span class=\"vlist-t\"><span class=\"vlist-r\"><span class=\"vlist\" style=\"height:0.7401em;\"><span style=\"top:-2.989em;margin-right:0.05em;\"><span class=\"pstrut\" style=\"height:2.7em;\"></span><span class=\"sizing reset-size6 size3 mtight\"><span class=\"mord mtight\">2</span></span></span></span></span></span></span></span></span></span><span style=\"top:-2.9151em;\"><span class=\"pstrut\" style=\"height:3em;\"></span><span class=\"hide-tail\" style=\"min-width:0.853em;height:1.08em;\"><svg xmlns=\"http://www.w3.org/2000/svg\" width=\"400em\" height=\"1.08em\" viewBox=\"0 0 400000 1080\" preserveAspectRatio=\"xMinYMin slice\"><path d=\"M95,702\nc-2.7,0,-7.17,-2.7,-13.5,-8c-5.8,-5.3,-9.5,-10,-9.5,-14\nc0,-2,0.3,-3.3,1,-4c1.3,-2.7,23.83,-20.7,67.5,-54\nc44.2,-33.3,65.8,-50.3,66.5,-51c1.3,-1.3,3,-2,5,-2c4.7,0,8.7,3.3,12,10\ns173,378,173,378c0.7,0,35.3,-71,104,-213c68.7,-142,137.5,-285,206.5,-429\nc69,-144,104.5,-217.7,106.5,-221\nl0 -0\nc5.3,-9.3,12,-14,20,-14\nH400000v40H845.2724\ns-225.272,467,-225.272,467s-235,486,-235,486c-2.7,4.7,-9,7,-19,7\nc-6,0,-10,-1,-12,-3s-194,-422,-194,-422s-65,47,-65,47z\nM834 80h400000v40h-400000z\"></path></svg></span></span></span><span class=\"vlist-s\">​</span></span><span class=\"vlist-r\"><span class=\"vlist\" style=\"height:0.0849em;\"><span></span></span></span></span></span><span class=\"mord mathnormal\" style=\"margin-right:0.03588em;\">σ</span><span class=\"mopen\">(</span><span class=\"mord mathnormal\" style=\"margin-right:0.07847em;\">X</span><span class=\"mclose\">)</span></span></span></span></span>.</p></li>\n</ul>\n</div>\n<h2 id=\"somme-de-plusieurs-variables-aleatoires\">Somme de plusieurs variables aléatoires</h2>\n<h3 id=\"definition-et-proprietes\">Définition et propriétés</h3>\n<p>Nous allons tenter de généraliser un petit peu le concept vu dans la\nsection précédente. En effet, au lieu d’étudier la somme de deux\nvariables aléatoires, on va étudier la somme de <span class=\"math-rendered\" data-latex=\"n\" data-latex-display=\"false\"><span class=\"katex\"><span class=\"katex-html\" aria-hidden=\"true\"><span class=\"base\"><span class=\"strut\" style=\"height:0.4306em;\"></span><span class=\"mord mathnormal\">n</span></span></span></span></span>\nvariables aléatoires.</p>\n<p>En classe de Terminale, on se limite au cas où ces variables\naléatoires suivent une même loi.</p>\n<div id=\"formula-4\" class=\"bubble\" data-variant=\"formula\">\n<h4>Échantillon aléatoire</h4>\n<p>Un <span class=\"math-rendered\" data-latex=\"n\" data-latex-display=\"false\"><span class=\"katex\"><span class=\"katex-html\" aria-hidden=\"true\"><span class=\"base\"><span class=\"strut\" style=\"height:0.4306em;\"></span><span class=\"mord mathnormal\">n</span></span></span></span></span>-uplet de variables aléatoires <span class=\"math-rendered\" data-latex=\"(X_1, X_2, \\dots, X_n)\" data-latex-display=\"false\"><span class=\"katex\"><span class=\"katex-html\" aria-hidden=\"true\"><span class=\"base\"><span class=\"strut\" style=\"height:1em;vertical-align:-0.25em;\"></span><span class=\"mopen\">(</span><span class=\"mord\"><span class=\"mord mathnormal\" style=\"margin-right:0.07847em;\">X</span><span class=\"msupsub\"><span class=\"vlist-t vlist-t2\"><span class=\"vlist-r\"><span class=\"vlist\" style=\"height:0.3011em;\"><span style=\"top:-2.55em;margin-left:-0.0785em;margin-right:0.05em;\"><span class=\"pstrut\" style=\"height:2.7em;\"></span><span class=\"sizing reset-size6 size3 mtight\"><span class=\"mord mtight\">1</span></span></span></span><span class=\"vlist-s\">​</span></span><span class=\"vlist-r\"><span class=\"vlist\" style=\"height:0.15em;\"><span></span></span></span></span></span></span><span class=\"mpunct\">,</span><span class=\"mspace\" style=\"margin-right:0.1667em;\"></span><span class=\"mord\"><span class=\"mord mathnormal\" style=\"margin-right:0.07847em;\">X</span><span class=\"msupsub\"><span class=\"vlist-t vlist-t2\"><span class=\"vlist-r\"><span class=\"vlist\" style=\"height:0.3011em;\"><span style=\"top:-2.55em;margin-left:-0.0785em;margin-right:0.05em;\"><span class=\"pstrut\" style=\"height:2.7em;\"></span><span class=\"sizing reset-size6 size3 mtight\"><span class=\"mord mtight\">2</span></span></span></span><span class=\"vlist-s\">​</span></span><span class=\"vlist-r\"><span class=\"vlist\" style=\"height:0.15em;\"><span></span></span></span></span></span></span><span class=\"mpunct\">,</span><span class=\"mspace\" style=\"margin-right:0.1667em;\"></span><span class=\"minner\">…</span><span class=\"mspace\" style=\"margin-right:0.1667em;\"></span><span class=\"mpunct\">,</span><span class=\"mspace\" style=\"margin-right:0.1667em;\"></span><span class=\"mord\"><span class=\"mord mathnormal\" style=\"margin-right:0.07847em;\">X</span><span class=\"msupsub\"><span class=\"vlist-t vlist-t2\"><span class=\"vlist-r\"><span class=\"vlist\" style=\"height:0.1514em;\"><span style=\"top:-2.55em;margin-left:-0.0785em;margin-right:0.05em;\"><span class=\"pstrut\" style=\"height:2.7em;\"></span><span class=\"sizing reset-size6 size3 mtight\"><span class=\"mord mathnormal mtight\">n</span></span></span></span><span class=\"vlist-s\">​</span></span><span class=\"vlist-r\"><span class=\"vlist\" style=\"height:0.15em;\"><span></span></span></span></span></span></span><span class=\"mclose\">)</span></span></span></span></span> qui sont toutes indépendantes et\nqui suivent une même loi de probabilité est appelé <strong>échantillon\naléatoire de taille <span class=\"math-rendered\" data-latex=\"n\" data-latex-display=\"false\"><span class=\"katex\"><span class=\"katex-html\" aria-hidden=\"true\"><span class=\"base\"><span class=\"strut\" style=\"height:0.4306em;\"></span><span class=\"mord mathnormal\">n</span></span></span></span></span> associé à cette\nloi</strong>.</p>\n</div>\n<div id=\"formula-5\" class=\"bubble\" data-variant=\"formula\">\n<h4>Espérance de variables aléatoires de même loi</h4>\n<p>Soit <span class=\"math-rendered\" data-latex=\"(X_1, X_2, \\dots, X_n)\" data-latex-display=\"false\"><span class=\"katex\"><span class=\"katex-html\" aria-hidden=\"true\"><span class=\"base\"><span class=\"strut\" style=\"height:1em;vertical-align:-0.25em;\"></span><span class=\"mopen\">(</span><span class=\"mord\"><span class=\"mord mathnormal\" style=\"margin-right:0.07847em;\">X</span><span class=\"msupsub\"><span class=\"vlist-t vlist-t2\"><span class=\"vlist-r\"><span class=\"vlist\" style=\"height:0.3011em;\"><span style=\"top:-2.55em;margin-left:-0.0785em;margin-right:0.05em;\"><span class=\"pstrut\" style=\"height:2.7em;\"></span><span class=\"sizing reset-size6 size3 mtight\"><span class=\"mord mtight\">1</span></span></span></span><span class=\"vlist-s\">​</span></span><span class=\"vlist-r\"><span class=\"vlist\" style=\"height:0.15em;\"><span></span></span></span></span></span></span><span class=\"mpunct\">,</span><span class=\"mspace\" style=\"margin-right:0.1667em;\"></span><span class=\"mord\"><span class=\"mord mathnormal\" style=\"margin-right:0.07847em;\">X</span><span class=\"msupsub\"><span class=\"vlist-t vlist-t2\"><span class=\"vlist-r\"><span class=\"vlist\" style=\"height:0.3011em;\"><span style=\"top:-2.55em;margin-left:-0.0785em;margin-right:0.05em;\"><span class=\"pstrut\" style=\"height:2.7em;\"></span><span class=\"sizing reset-size6 size3 mtight\"><span class=\"mord mtight\">2</span></span></span></span><span class=\"vlist-s\">​</span></span><span class=\"vlist-r\"><span class=\"vlist\" style=\"height:0.15em;\"><span></span></span></span></span></span></span><span class=\"mpunct\">,</span><span class=\"mspace\" style=\"margin-right:0.1667em;\"></span><span class=\"minner\">…</span><span class=\"mspace\" style=\"margin-right:0.1667em;\"></span><span class=\"mpunct\">,</span><span class=\"mspace\" style=\"margin-right:0.1667em;\"></span><span class=\"mord\"><span class=\"mord mathnormal\" style=\"margin-right:0.07847em;\">X</span><span class=\"msupsub\"><span class=\"vlist-t vlist-t2\"><span class=\"vlist-r\"><span class=\"vlist\" style=\"height:0.1514em;\"><span style=\"top:-2.55em;margin-left:-0.0785em;margin-right:0.05em;\"><span class=\"pstrut\" style=\"height:2.7em;\"></span><span class=\"sizing reset-size6 size3 mtight\"><span class=\"mord mathnormal mtight\">n</span></span></span></span><span class=\"vlist-s\">​</span></span><span class=\"vlist-r\"><span class=\"vlist\" style=\"height:0.15em;\"><span></span></span></span></span></span></span><span class=\"mclose\">)</span></span></span></span></span> un échantillon\naléatoire de taille <span class=\"math-rendered\" data-latex=\"n\" data-latex-display=\"false\"><span class=\"katex\"><span class=\"katex-html\" aria-hidden=\"true\"><span class=\"base\"><span class=\"strut\" style=\"height:0.4306em;\"></span><span class=\"mord mathnormal\">n</span></span></span></span></span>. On pose <span class=\"math-rendered\" data-latex=\"S_n = X_1 + X_2 + \\dots + X_n\" data-latex-display=\"false\"><span class=\"katex\"><span class=\"katex-html\" aria-hidden=\"true\"><span class=\"base\"><span class=\"strut\" style=\"height:0.8333em;vertical-align:-0.15em;\"></span><span class=\"mord\"><span class=\"mord mathnormal\" style=\"margin-right:0.05764em;\">S</span><span class=\"msupsub\"><span class=\"vlist-t vlist-t2\"><span class=\"vlist-r\"><span class=\"vlist\" style=\"height:0.1514em;\"><span style=\"top:-2.55em;margin-left:-0.0576em;margin-right:0.05em;\"><span class=\"pstrut\" style=\"height:2.7em;\"></span><span class=\"sizing reset-size6 size3 mtight\"><span class=\"mord mathnormal mtight\">n</span></span></span></span><span class=\"vlist-s\">​</span></span><span class=\"vlist-r\"><span class=\"vlist\" style=\"height:0.15em;\"><span></span></span></span></span></span></span><span class=\"mspace\" style=\"margin-right:0.2778em;\"></span><span class=\"mrel\">=</span><span class=\"mspace\" style=\"margin-right:0.2778em;\"></span></span><span class=\"base\"><span class=\"strut\" style=\"height:0.8333em;vertical-align:-0.15em;\"></span><span class=\"mord\"><span class=\"mord mathnormal\" style=\"margin-right:0.07847em;\">X</span><span class=\"msupsub\"><span class=\"vlist-t vlist-t2\"><span class=\"vlist-r\"><span class=\"vlist\" style=\"height:0.3011em;\"><span style=\"top:-2.55em;margin-left:-0.0785em;margin-right:0.05em;\"><span class=\"pstrut\" style=\"height:2.7em;\"></span><span class=\"sizing reset-size6 size3 mtight\"><span class=\"mord mtight\">1</span></span></span></span><span class=\"vlist-s\">​</span></span><span class=\"vlist-r\"><span class=\"vlist\" style=\"height:0.15em;\"><span></span></span></span></span></span></span><span class=\"mspace\" style=\"margin-right:0.2222em;\"></span><span class=\"mbin\">+</span><span class=\"mspace\" style=\"margin-right:0.2222em;\"></span></span><span class=\"base\"><span class=\"strut\" style=\"height:0.8333em;vertical-align:-0.15em;\"></span><span class=\"mord\"><span class=\"mord mathnormal\" style=\"margin-right:0.07847em;\">X</span><span class=\"msupsub\"><span class=\"vlist-t vlist-t2\"><span class=\"vlist-r\"><span class=\"vlist\" style=\"height:0.3011em;\"><span style=\"top:-2.55em;margin-left:-0.0785em;margin-right:0.05em;\"><span class=\"pstrut\" style=\"height:2.7em;\"></span><span class=\"sizing reset-size6 size3 mtight\"><span class=\"mord mtight\">2</span></span></span></span><span class=\"vlist-s\">​</span></span><span class=\"vlist-r\"><span class=\"vlist\" style=\"height:0.15em;\"><span></span></span></span></span></span></span><span class=\"mspace\" style=\"margin-right:0.2222em;\"></span><span class=\"mbin\">+</span><span class=\"mspace\" style=\"margin-right:0.2222em;\"></span></span><span class=\"base\"><span class=\"strut\" style=\"height:0.6667em;vertical-align:-0.0833em;\"></span><span class=\"minner\">⋯</span><span class=\"mspace\" style=\"margin-right:0.2222em;\"></span><span class=\"mbin\">+</span><span class=\"mspace\" style=\"margin-right:0.2222em;\"></span></span><span class=\"base\"><span class=\"strut\" style=\"height:0.8333em;vertical-align:-0.15em;\"></span><span class=\"mord\"><span class=\"mord mathnormal\" style=\"margin-right:0.07847em;\">X</span><span class=\"msupsub\"><span class=\"vlist-t vlist-t2\"><span class=\"vlist-r\"><span class=\"vlist\" style=\"height:0.1514em;\"><span style=\"top:-2.55em;margin-left:-0.0785em;margin-right:0.05em;\"><span class=\"pstrut\" style=\"height:2.7em;\"></span><span class=\"sizing reset-size6 size3 mtight\"><span class=\"mord mathnormal mtight\">n</span></span></span></span><span class=\"vlist-s\">​</span></span><span class=\"vlist-r\"><span class=\"vlist\" style=\"height:0.15em;\"><span></span></span></span></span></span></span></span></span></span></span> et <span class=\"math-rendered\" data-latex=\"M_n = \\frac{S_n}{n}\" data-latex-display=\"false\"><span class=\"katex\"><span class=\"katex-html\" aria-hidden=\"true\"><span class=\"base\"><span class=\"strut\" style=\"height:0.8333em;vertical-align:-0.15em;\"></span><span class=\"mord\"><span class=\"mord mathnormal\" style=\"margin-right:0.10903em;\">M</span><span class=\"msupsub\"><span class=\"vlist-t vlist-t2\"><span class=\"vlist-r\"><span class=\"vlist\" style=\"height:0.1514em;\"><span style=\"top:-2.55em;margin-left:-0.109em;margin-right:0.05em;\"><span class=\"pstrut\" style=\"height:2.7em;\"></span><span class=\"sizing reset-size6 size3 mtight\"><span class=\"mord mathnormal mtight\">n</span></span></span></span><span class=\"vlist-s\">​</span></span><span class=\"vlist-r\"><span class=\"vlist\" style=\"height:0.15em;\"><span></span></span></span></span></span></span><span class=\"mspace\" style=\"margin-right:0.2778em;\"></span><span class=\"mrel\">=</span><span class=\"mspace\" style=\"margin-right:0.2778em;\"></span></span><span class=\"base\"><span class=\"strut\" style=\"height:1.2334em;vertical-align:-0.345em;\"></span><span class=\"mord\"><span class=\"mopen nulldelimiter\"></span><span class=\"mfrac\"><span class=\"vlist-t vlist-t2\"><span class=\"vlist-r\"><span class=\"vlist\" style=\"height:0.8884em;\"><span style=\"top:-2.655em;\"><span class=\"pstrut\" style=\"height:3em;\"></span><span class=\"sizing reset-size6 size3 mtight\"><span class=\"mord mtight\"><span class=\"mord mathnormal mtight\">n</span></span></span></span><span style=\"top:-3.23em;\"><span class=\"pstrut\" style=\"height:3em;\"></span><span class=\"frac-line\" style=\"border-bottom-width:0.04em;\"></span></span><span style=\"top:-3.4101em;\"><span class=\"pstrut\" style=\"height:3em;\"></span><span class=\"sizing reset-size6 size3 mtight\"><span class=\"mord mtight\"><span class=\"mord mtight\"><span class=\"mord mathnormal mtight\" style=\"margin-right:0.05764em;\">S</span><span class=\"msupsub\"><span class=\"vlist-t vlist-t2\"><span class=\"vlist-r\"><span class=\"vlist\" style=\"height:0.1645em;\"><span style=\"top:-2.357em;margin-left:-0.0576em;margin-right:0.0714em;\"><span class=\"pstrut\" style=\"height:2.5em;\"></span><span class=\"sizing reset-size3 size1 mtight\"><span class=\"mord mathnormal mtight\">n</span></span></span></span><span class=\"vlist-s\">​</span></span><span class=\"vlist-r\"><span class=\"vlist\" style=\"height:0.143em;\"><span></span></span></span></span></span></span></span></span></span></span><span class=\"vlist-s\">​</span></span><span class=\"vlist-r\"><span class=\"vlist\" style=\"height:0.345em;\"><span></span></span></span></span></span><span class=\"mclose nulldelimiter\"></span></span></span></span></span></span>.\nAlors :</p>\n<ul>\n<li><p><span class=\"math-rendered\" data-latex=\"E(S_n) = nE(X_1)\" data-latex-display=\"false\"><span class=\"katex\"><span class=\"katex-html\" aria-hidden=\"true\"><span class=\"base\"><span class=\"strut\" style=\"height:1em;vertical-align:-0.25em;\"></span><span class=\"mord mathnormal\" style=\"margin-right:0.05764em;\">E</span><span class=\"mopen\">(</span><span class=\"mord\"><span class=\"mord mathnormal\" style=\"margin-right:0.05764em;\">S</span><span class=\"msupsub\"><span class=\"vlist-t vlist-t2\"><span class=\"vlist-r\"><span class=\"vlist\" style=\"height:0.1514em;\"><span style=\"top:-2.55em;margin-left:-0.0576em;margin-right:0.05em;\"><span class=\"pstrut\" style=\"height:2.7em;\"></span><span class=\"sizing reset-size6 size3 mtight\"><span class=\"mord mathnormal mtight\">n</span></span></span></span><span class=\"vlist-s\">​</span></span><span class=\"vlist-r\"><span class=\"vlist\" style=\"height:0.15em;\"><span></span></span></span></span></span></span><span class=\"mclose\">)</span><span class=\"mspace\" style=\"margin-right:0.2778em;\"></span><span class=\"mrel\">=</span><span class=\"mspace\" style=\"margin-right:0.2778em;\"></span></span><span class=\"base\"><span class=\"strut\" style=\"height:1em;vertical-align:-0.25em;\"></span><span class=\"mord mathnormal\">n</span><span class=\"mord mathnormal\" style=\"margin-right:0.05764em;\">E</span><span class=\"mopen\">(</span><span class=\"mord\"><span class=\"mord mathnormal\" style=\"margin-right:0.07847em;\">X</span><span class=\"msupsub\"><span class=\"vlist-t vlist-t2\"><span class=\"vlist-r\"><span class=\"vlist\" style=\"height:0.3011em;\"><span style=\"top:-2.55em;margin-left:-0.0785em;margin-right:0.05em;\"><span class=\"pstrut\" style=\"height:2.7em;\"></span><span class=\"sizing reset-size6 size3 mtight\"><span class=\"mord mtight\">1</span></span></span></span><span class=\"vlist-s\">​</span></span><span class=\"vlist-r\"><span class=\"vlist\" style=\"height:0.15em;\"><span></span></span></span></span></span></span><span class=\"mclose\">)</span></span></span></span></span> et <span class=\"math-rendered\" data-latex=\"V(S_n) = nV(X_1)\" data-latex-display=\"false\"><span class=\"katex\"><span class=\"katex-html\" aria-hidden=\"true\"><span class=\"base\"><span class=\"strut\" style=\"height:1em;vertical-align:-0.25em;\"></span><span class=\"mord mathnormal\" style=\"margin-right:0.22222em;\">V</span><span class=\"mopen\">(</span><span class=\"mord\"><span class=\"mord mathnormal\" style=\"margin-right:0.05764em;\">S</span><span class=\"msupsub\"><span class=\"vlist-t vlist-t2\"><span class=\"vlist-r\"><span class=\"vlist\" style=\"height:0.1514em;\"><span style=\"top:-2.55em;margin-left:-0.0576em;margin-right:0.05em;\"><span class=\"pstrut\" style=\"height:2.7em;\"></span><span class=\"sizing reset-size6 size3 mtight\"><span class=\"mord mathnormal mtight\">n</span></span></span></span><span class=\"vlist-s\">​</span></span><span class=\"vlist-r\"><span class=\"vlist\" style=\"height:0.15em;\"><span></span></span></span></span></span></span><span class=\"mclose\">)</span><span class=\"mspace\" style=\"margin-right:0.2778em;\"></span><span class=\"mrel\">=</span><span class=\"mspace\" style=\"margin-right:0.2778em;\"></span></span><span class=\"base\"><span class=\"strut\" style=\"height:1em;vertical-align:-0.25em;\"></span><span class=\"mord mathnormal\" style=\"margin-right:0.22222em;\">nV</span><span class=\"mopen\">(</span><span class=\"mord\"><span class=\"mord mathnormal\" style=\"margin-right:0.07847em;\">X</span><span class=\"msupsub\"><span class=\"vlist-t vlist-t2\"><span class=\"vlist-r\"><span class=\"vlist\" style=\"height:0.3011em;\"><span style=\"top:-2.55em;margin-left:-0.0785em;margin-right:0.05em;\"><span class=\"pstrut\" style=\"height:2.7em;\"></span><span class=\"sizing reset-size6 size3 mtight\"><span class=\"mord mtight\">1</span></span></span></span><span class=\"vlist-s\">​</span></span><span class=\"vlist-r\"><span class=\"vlist\" style=\"height:0.15em;\"><span></span></span></span></span></span></span><span class=\"mclose\">)</span></span></span></span></span>.</p></li>\n<li><p><span class=\"math-rendered\" data-latex=\"E(M_n) = E\\left(\\frac{S_n}{n}\\right) = \\frac{E(S_n)}{n} = E(X_1)\" data-latex-display=\"false\"><span class=\"katex\"><span class=\"katex-html\" aria-hidden=\"true\"><span class=\"base\"><span class=\"strut\" style=\"height:1em;vertical-align:-0.25em;\"></span><span class=\"mord mathnormal\" style=\"margin-right:0.05764em;\">E</span><span class=\"mopen\">(</span><span class=\"mord\"><span class=\"mord mathnormal\" style=\"margin-right:0.10903em;\">M</span><span class=\"msupsub\"><span class=\"vlist-t vlist-t2\"><span class=\"vlist-r\"><span class=\"vlist\" style=\"height:0.1514em;\"><span style=\"top:-2.55em;margin-left:-0.109em;margin-right:0.05em;\"><span class=\"pstrut\" style=\"height:2.7em;\"></span><span class=\"sizing reset-size6 size3 mtight\"><span class=\"mord mathnormal mtight\">n</span></span></span></span><span class=\"vlist-s\">​</span></span><span class=\"vlist-r\"><span class=\"vlist\" style=\"height:0.15em;\"><span></span></span></span></span></span></span><span class=\"mclose\">)</span><span class=\"mspace\" style=\"margin-right:0.2778em;\"></span><span class=\"mrel\">=</span><span class=\"mspace\" style=\"margin-right:0.2778em;\"></span></span><span class=\"base\"><span class=\"strut\" style=\"height:1.2384em;vertical-align:-0.35em;\"></span><span class=\"mord mathnormal\" style=\"margin-right:0.05764em;\">E</span><span class=\"mspace\" style=\"margin-right:0.1667em;\"></span><span class=\"minner\"><span class=\"mopen delimcenter\" style=\"top:0em;\"><span class=\"delimsizing size1\">(</span></span><span class=\"mord\"><span class=\"mopen nulldelimiter\"></span><span class=\"mfrac\"><span class=\"vlist-t vlist-t2\"><span class=\"vlist-r\"><span class=\"vlist\" style=\"height:0.8884em;\"><span style=\"top:-2.655em;\"><span class=\"pstrut\" style=\"height:3em;\"></span><span class=\"sizing reset-size6 size3 mtight\"><span class=\"mord mtight\"><span class=\"mord mathnormal mtight\">n</span></span></span></span><span style=\"top:-3.23em;\"><span class=\"pstrut\" style=\"height:3em;\"></span><span class=\"frac-line\" style=\"border-bottom-width:0.04em;\"></span></span><span style=\"top:-3.4101em;\"><span class=\"pstrut\" style=\"height:3em;\"></span><span class=\"sizing reset-size6 size3 mtight\"><span class=\"mord mtight\"><span class=\"mord mtight\"><span class=\"mord mathnormal mtight\" style=\"margin-right:0.05764em;\">S</span><span class=\"msupsub\"><span class=\"vlist-t vlist-t2\"><span class=\"vlist-r\"><span class=\"vlist\" style=\"height:0.1645em;\"><span style=\"top:-2.357em;margin-left:-0.0576em;margin-right:0.0714em;\"><span class=\"pstrut\" style=\"height:2.5em;\"></span><span class=\"sizing reset-size3 size1 mtight\"><span class=\"mord mathnormal mtight\">n</span></span></span></span><span class=\"vlist-s\">​</span></span><span class=\"vlist-r\"><span class=\"vlist\" style=\"height:0.143em;\"><span></span></span></span></span></span></span></span></span></span></span><span class=\"vlist-s\">​</span></span><span class=\"vlist-r\"><span class=\"vlist\" style=\"height:0.345em;\"><span></span></span></span></span></span><span class=\"mclose nulldelimiter\"></span></span><span class=\"mclose delimcenter\" style=\"top:0em;\"><span class=\"delimsizing size1\">)</span></span></span><span class=\"mspace\" style=\"margin-right:0.2778em;\"></span><span class=\"mrel\">=</span><span class=\"mspace\" style=\"margin-right:0.2778em;\"></span></span><span class=\"base\"><span class=\"strut\" style=\"height:1.355em;vertical-align:-0.345em;\"></span><span class=\"mord\"><span class=\"mopen nulldelimiter\"></span><span class=\"mfrac\"><span class=\"vlist-t vlist-t2\"><span class=\"vlist-r\"><span class=\"vlist\" style=\"height:1.01em;\"><span style=\"top:-2.655em;\"><span class=\"pstrut\" style=\"height:3em;\"></span><span class=\"sizing reset-size6 size3 mtight\"><span class=\"mord mtight\"><span class=\"mord mathnormal mtight\">n</span></span></span></span><span style=\"top:-3.23em;\"><span class=\"pstrut\" style=\"height:3em;\"></span><span class=\"frac-line\" style=\"border-bottom-width:0.04em;\"></span></span><span style=\"top:-3.485em;\"><span class=\"pstrut\" style=\"height:3em;\"></span><span class=\"sizing reset-size6 size3 mtight\"><span class=\"mord mtight\"><span class=\"mord mathnormal mtight\" style=\"margin-right:0.05764em;\">E</span><span class=\"mopen mtight\">(</span><span class=\"mord mtight\"><span class=\"mord mathnormal mtight\" style=\"margin-right:0.05764em;\">S</span><span class=\"msupsub\"><span class=\"vlist-t vlist-t2\"><span class=\"vlist-r\"><span class=\"vlist\" style=\"height:0.1645em;\"><span style=\"top:-2.357em;margin-left:-0.0576em;margin-right:0.0714em;\"><span class=\"pstrut\" style=\"height:2.5em;\"></span><span class=\"sizing reset-size3 size1 mtight\"><span class=\"mord mathnormal mtight\">n</span></span></span></span><span class=\"vlist-s\">​</span></span><span class=\"vlist-r\"><span class=\"vlist\" style=\"height:0.143em;\"><span></span></span></span></span></span></span><span class=\"mclose mtight\">)</span></span></span></span></span><span class=\"vlist-s\">​</span></span><span class=\"vlist-r\"><span class=\"vlist\" style=\"height:0.345em;\"><span></span></span></span></span></span><span class=\"mclose nulldelimiter\"></span></span><span class=\"mspace\" style=\"margin-right:0.2778em;\"></span><span class=\"mrel\">=</span><span class=\"mspace\" style=\"margin-right:0.2778em;\"></span></span><span class=\"base\"><span class=\"strut\" style=\"height:1em;vertical-align:-0.25em;\"></span><span class=\"mord mathnormal\" style=\"margin-right:0.05764em;\">E</span><span class=\"mopen\">(</span><span class=\"mord\"><span class=\"mord mathnormal\" style=\"margin-right:0.07847em;\">X</span><span class=\"msupsub\"><span class=\"vlist-t vlist-t2\"><span class=\"vlist-r\"><span class=\"vlist\" style=\"height:0.3011em;\"><span style=\"top:-2.55em;margin-left:-0.0785em;margin-right:0.05em;\"><span class=\"pstrut\" style=\"height:2.7em;\"></span><span class=\"sizing reset-size6 size3 mtight\"><span class=\"mord mtight\">1</span></span></span></span><span class=\"vlist-s\">​</span></span><span class=\"vlist-r\"><span class=\"vlist\" style=\"height:0.15em;\"><span></span></span></span></span></span></span><span class=\"mclose\">)</span></span></span></span></span> et <span class=\"math-rendered\" data-latex=\"V(M_n) = \\frac{V(S_n)}{n^2} = \\frac{V(X_1)}{n}\" data-latex-display=\"false\"><span class=\"katex\"><span class=\"katex-html\" aria-hidden=\"true\"><span class=\"base\"><span class=\"strut\" style=\"height:1em;vertical-align:-0.25em;\"></span><span class=\"mord mathnormal\" style=\"margin-right:0.22222em;\">V</span><span class=\"mopen\">(</span><span class=\"mord\"><span class=\"mord mathnormal\" style=\"margin-right:0.10903em;\">M</span><span class=\"msupsub\"><span class=\"vlist-t vlist-t2\"><span class=\"vlist-r\"><span class=\"vlist\" style=\"height:0.1514em;\"><span style=\"top:-2.55em;margin-left:-0.109em;margin-right:0.05em;\"><span class=\"pstrut\" style=\"height:2.7em;\"></span><span class=\"sizing reset-size6 size3 mtight\"><span class=\"mord mathnormal mtight\">n</span></span></span></span><span class=\"vlist-s\">​</span></span><span class=\"vlist-r\"><span class=\"vlist\" style=\"height:0.15em;\"><span></span></span></span></span></span></span><span class=\"mclose\">)</span><span class=\"mspace\" style=\"margin-right:0.2778em;\"></span><span class=\"mrel\">=</span><span class=\"mspace\" style=\"margin-right:0.2778em;\"></span></span><span class=\"base\"><span class=\"strut\" style=\"height:1.355em;vertical-align:-0.345em;\"></span><span class=\"mord\"><span class=\"mopen nulldelimiter\"></span><span class=\"mfrac\"><span class=\"vlist-t vlist-t2\"><span class=\"vlist-r\"><span class=\"vlist\" style=\"height:1.01em;\"><span style=\"top:-2.655em;\"><span class=\"pstrut\" style=\"height:3em;\"></span><span class=\"sizing reset-size6 size3 mtight\"><span class=\"mord mtight\"><span class=\"mord mtight\"><span class=\"mord mathnormal mtight\">n</span><span class=\"msupsub\"><span class=\"vlist-t\"><span class=\"vlist-r\"><span class=\"vlist\" style=\"height:0.7463em;\"><span style=\"top:-2.786em;margin-right:0.0714em;\"><span class=\"pstrut\" style=\"height:2.5em;\"></span><span class=\"sizing reset-size3 size1 mtight\"><span class=\"mord mtight\">2</span></span></span></span></span></span></span></span></span></span></span><span style=\"top:-3.23em;\"><span class=\"pstrut\" style=\"height:3em;\"></span><span class=\"frac-line\" style=\"border-bottom-width:0.04em;\"></span></span><span style=\"top:-3.485em;\"><span class=\"pstrut\" style=\"height:3em;\"></span><span class=\"sizing reset-size6 size3 mtight\"><span class=\"mord mtight\"><span class=\"mord mathnormal mtight\" style=\"margin-right:0.22222em;\">V</span><span class=\"mopen mtight\">(</span><span class=\"mord mtight\"><span class=\"mord mathnormal mtight\" style=\"margin-right:0.05764em;\">S</span><span class=\"msupsub\"><span class=\"vlist-t vlist-t2\"><span class=\"vlist-r\"><span class=\"vlist\" style=\"height:0.1645em;\"><span style=\"top:-2.357em;margin-left:-0.0576em;margin-right:0.0714em;\"><span class=\"pstrut\" style=\"height:2.5em;\"></span><span class=\"sizing reset-size3 size1 mtight\"><span class=\"mord mathnormal mtight\">n</span></span></span></span><span class=\"vlist-s\">​</span></span><span class=\"vlist-r\"><span class=\"vlist\" style=\"height:0.143em;\"><span></span></span></span></span></span></span><span class=\"mclose mtight\">)</span></span></span></span></span><span class=\"vlist-s\">​</span></span><span class=\"vlist-r\"><span class=\"vlist\" style=\"height:0.345em;\"><span></span></span></span></span></span><span class=\"mclose nulldelimiter\"></span></span><span class=\"mspace\" style=\"margin-right:0.2778em;\"></span><span class=\"mrel\">=</span><span class=\"mspace\" style=\"margin-right:0.2778em;\"></span></span><span class=\"base\"><span class=\"strut\" style=\"height:1.355em;vertical-align:-0.345em;\"></span><span class=\"mord\"><span class=\"mopen nulldelimiter\"></span><span class=\"mfrac\"><span class=\"vlist-t vlist-t2\"><span class=\"vlist-r\"><span class=\"vlist\" style=\"height:1.01em;\"><span style=\"top:-2.655em;\"><span class=\"pstrut\" style=\"height:3em;\"></span><span class=\"sizing reset-size6 size3 mtight\"><span class=\"mord mtight\"><span class=\"mord mathnormal mtight\">n</span></span></span></span><span style=\"top:-3.23em;\"><span class=\"pstrut\" style=\"height:3em;\"></span><span class=\"frac-line\" style=\"border-bottom-width:0.04em;\"></span></span><span style=\"top:-3.485em;\"><span class=\"pstrut\" style=\"height:3em;\"></span><span class=\"sizing reset-size6 size3 mtight\"><span class=\"mord mtight\"><span class=\"mord mathnormal mtight\" style=\"margin-right:0.22222em;\">V</span><span class=\"mopen mtight\">(</span><span class=\"mord mtight\"><span class=\"mord mathnormal mtight\" style=\"margin-right:0.07847em;\">X</span><span class=\"msupsub\"><span class=\"vlist-t vlist-t2\"><span class=\"vlist-r\"><span class=\"vlist\" style=\"height:0.3173em;\"><span style=\"top:-2.357em;margin-left:-0.0785em;margin-right:0.0714em;\"><span class=\"pstrut\" style=\"height:2.5em;\"></span><span class=\"sizing reset-size3 size1 mtight\"><span class=\"mord mtight\">1</span></span></span></span><span class=\"vlist-s\">​</span></span><span class=\"vlist-r\"><span class=\"vlist\" style=\"height:0.143em;\"><span></span></span></span></span></span></span><span class=\"mclose mtight\">)</span></span></span></span></span><span class=\"vlist-s\">​</span></span><span class=\"vlist-r\"><span class=\"vlist\" style=\"height:0.345em;\"><span></span></span></span></span></span><span class=\"mclose nulldelimiter\"></span></span></span></span></span></span>.</p></li>\n</ul>\n</div>\n\n<h3 id=\"somme--decompositions-de-certaines-variables-aleatoires\">Somme / décompositions de certaines variables aléatoires</h3>\n<p>Nous allons maintenant énoncer une propriété utile qui permet de\ntrouver la loi suivie par une somme de variables aléatoires\nindépendantes suivant une loi de Bernoulli.</p>\n<div id=\"formula-6\" class=\"bubble\" data-variant=\"formula\">\n<h4>Somme de variables aléatoires indépendantes suivant une même loi de\nBernoulli</h4>\n<p>Soit <span class=\"math-rendered\" data-latex=\"(X_1, X_2, \\dots, X_n)\" data-latex-display=\"false\"><span class=\"katex\"><span class=\"katex-html\" aria-hidden=\"true\"><span class=\"base\"><span class=\"strut\" style=\"height:1em;vertical-align:-0.25em;\"></span><span class=\"mopen\">(</span><span class=\"mord\"><span class=\"mord mathnormal\" style=\"margin-right:0.07847em;\">X</span><span class=\"msupsub\"><span class=\"vlist-t vlist-t2\"><span class=\"vlist-r\"><span class=\"vlist\" style=\"height:0.3011em;\"><span style=\"top:-2.55em;margin-left:-0.0785em;margin-right:0.05em;\"><span class=\"pstrut\" style=\"height:2.7em;\"></span><span class=\"sizing reset-size6 size3 mtight\"><span class=\"mord mtight\">1</span></span></span></span><span class=\"vlist-s\">​</span></span><span class=\"vlist-r\"><span class=\"vlist\" style=\"height:0.15em;\"><span></span></span></span></span></span></span><span class=\"mpunct\">,</span><span class=\"mspace\" style=\"margin-right:0.1667em;\"></span><span class=\"mord\"><span class=\"mord mathnormal\" style=\"margin-right:0.07847em;\">X</span><span class=\"msupsub\"><span class=\"vlist-t vlist-t2\"><span class=\"vlist-r\"><span class=\"vlist\" style=\"height:0.3011em;\"><span style=\"top:-2.55em;margin-left:-0.0785em;margin-right:0.05em;\"><span class=\"pstrut\" style=\"height:2.7em;\"></span><span class=\"sizing reset-size6 size3 mtight\"><span class=\"mord mtight\">2</span></span></span></span><span class=\"vlist-s\">​</span></span><span class=\"vlist-r\"><span class=\"vlist\" style=\"height:0.15em;\"><span></span></span></span></span></span></span><span class=\"mpunct\">,</span><span class=\"mspace\" style=\"margin-right:0.1667em;\"></span><span class=\"minner\">…</span><span class=\"mspace\" style=\"margin-right:0.1667em;\"></span><span class=\"mpunct\">,</span><span class=\"mspace\" style=\"margin-right:0.1667em;\"></span><span class=\"mord\"><span class=\"mord mathnormal\" style=\"margin-right:0.07847em;\">X</span><span class=\"msupsub\"><span class=\"vlist-t vlist-t2\"><span class=\"vlist-r\"><span class=\"vlist\" style=\"height:0.1514em;\"><span style=\"top:-2.55em;margin-left:-0.0785em;margin-right:0.05em;\"><span class=\"pstrut\" style=\"height:2.7em;\"></span><span class=\"sizing reset-size6 size3 mtight\"><span class=\"mord mathnormal mtight\">n</span></span></span></span><span class=\"vlist-s\">​</span></span><span class=\"vlist-r\"><span class=\"vlist\" style=\"height:0.15em;\"><span></span></span></span></span></span></span><span class=\"mclose\">)</span></span></span></span></span> un échantillon\naléatoire de taille <span class=\"math-rendered\" data-latex=\"n\" data-latex-display=\"false\"><span class=\"katex\"><span class=\"katex-html\" aria-hidden=\"true\"><span class=\"base\"><span class=\"strut\" style=\"height:0.4306em;\"></span><span class=\"mord mathnormal\">n</span></span></span></span></span> associé à une loi de Bernoulli\nde paramètre <span class=\"math-rendered\" data-latex=\"p\" data-latex-display=\"false\"><span class=\"katex\"><span class=\"katex-html\" aria-hidden=\"true\"><span class=\"base\"><span class=\"strut\" style=\"height:0.625em;vertical-align:-0.1944em;\"></span><span class=\"mord mathnormal\">p</span></span></span></span></span>.</p>\n<p>Alors <span class=\"math-rendered\" data-latex=\"X_1 + X_2 + \\dots + X_n\" data-latex-display=\"false\"><span class=\"katex\"><span class=\"katex-html\" aria-hidden=\"true\"><span class=\"base\"><span class=\"strut\" style=\"height:0.8333em;vertical-align:-0.15em;\"></span><span class=\"mord\"><span class=\"mord mathnormal\" style=\"margin-right:0.07847em;\">X</span><span class=\"msupsub\"><span class=\"vlist-t vlist-t2\"><span class=\"vlist-r\"><span class=\"vlist\" style=\"height:0.3011em;\"><span style=\"top:-2.55em;margin-left:-0.0785em;margin-right:0.05em;\"><span class=\"pstrut\" style=\"height:2.7em;\"></span><span class=\"sizing reset-size6 size3 mtight\"><span class=\"mord mtight\">1</span></span></span></span><span class=\"vlist-s\">​</span></span><span class=\"vlist-r\"><span class=\"vlist\" style=\"height:0.15em;\"><span></span></span></span></span></span></span><span class=\"mspace\" style=\"margin-right:0.2222em;\"></span><span class=\"mbin\">+</span><span class=\"mspace\" style=\"margin-right:0.2222em;\"></span></span><span class=\"base\"><span class=\"strut\" style=\"height:0.8333em;vertical-align:-0.15em;\"></span><span class=\"mord\"><span class=\"mord mathnormal\" style=\"margin-right:0.07847em;\">X</span><span class=\"msupsub\"><span class=\"vlist-t vlist-t2\"><span class=\"vlist-r\"><span class=\"vlist\" style=\"height:0.3011em;\"><span style=\"top:-2.55em;margin-left:-0.0785em;margin-right:0.05em;\"><span class=\"pstrut\" style=\"height:2.7em;\"></span><span class=\"sizing reset-size6 size3 mtight\"><span class=\"mord mtight\">2</span></span></span></span><span class=\"vlist-s\">​</span></span><span class=\"vlist-r\"><span class=\"vlist\" style=\"height:0.15em;\"><span></span></span></span></span></span></span><span class=\"mspace\" style=\"margin-right:0.2222em;\"></span><span class=\"mbin\">+</span><span class=\"mspace\" style=\"margin-right:0.2222em;\"></span></span><span class=\"base\"><span class=\"strut\" style=\"height:0.6667em;vertical-align:-0.0833em;\"></span><span class=\"minner\">⋯</span><span class=\"mspace\" style=\"margin-right:0.2222em;\"></span><span class=\"mbin\">+</span><span class=\"mspace\" style=\"margin-right:0.2222em;\"></span></span><span class=\"base\"><span class=\"strut\" style=\"height:0.8333em;vertical-align:-0.15em;\"></span><span class=\"mord\"><span class=\"mord mathnormal\" style=\"margin-right:0.07847em;\">X</span><span class=\"msupsub\"><span class=\"vlist-t vlist-t2\"><span class=\"vlist-r\"><span class=\"vlist\" style=\"height:0.1514em;\"><span style=\"top:-2.55em;margin-left:-0.0785em;margin-right:0.05em;\"><span class=\"pstrut\" style=\"height:2.7em;\"></span><span class=\"sizing reset-size6 size3 mtight\"><span class=\"mord mathnormal mtight\">n</span></span></span></span><span class=\"vlist-s\">​</span></span><span class=\"vlist-r\"><span class=\"vlist\" style=\"height:0.15em;\"><span></span></span></span></span></span></span></span></span></span></span> suit une loi\nbinomiale <span class=\"math-rendered\" data-latex=\"\\mathcal{B}(n; p)\" data-latex-display=\"false\"><span class=\"katex\"><span class=\"katex-html\" aria-hidden=\"true\"><span class=\"base\"><span class=\"strut\" style=\"height:1em;vertical-align:-0.25em;\"></span><span class=\"mord mathcal\" style=\"margin-right:0.03041em;\">B</span><span class=\"mopen\">(</span><span class=\"mord mathnormal\">n</span><span class=\"mpunct\">;</span><span class=\"mspace\" style=\"margin-right:0.1667em;\"></span><span class=\"mord mathnormal\">p</span><span class=\"mclose\">)</span></span></span></span></span>.</p>\n</div>\n\n<p>Enfin, signalons qu’il existe une réciproque de la première propriété\nqui permet de <q>transformer</q> une variable aléatoire suivant une loi\nbinomiale en somme de variables aléatoires suivant une loi de\nBernoulli.</p>\n<div id=\"formula-7\" class=\"bubble\" data-variant=\"formula\">\n<h4>Décomposition d’une variable aléatoire suivant une loi\nbinomiale</h4>\n<p>Soit <span class=\"math-rendered\" data-latex=\"X\" data-latex-display=\"false\"><span class=\"katex\"><span class=\"katex-html\" aria-hidden=\"true\"><span class=\"base\"><span class=\"strut\" style=\"height:0.6833em;\"></span><span class=\"mord mathnormal\" style=\"margin-right:0.07847em;\">X</span></span></span></span></span> une variable aléatoire suivant une loi\nbinomiale <span class=\"math-rendered\" data-latex=\"\\mathcal{B}(n; p)\" data-latex-display=\"false\"><span class=\"katex\"><span class=\"katex-html\" aria-hidden=\"true\"><span class=\"base\"><span class=\"strut\" style=\"height:1em;vertical-align:-0.25em;\"></span><span class=\"mord mathcal\" style=\"margin-right:0.03041em;\">B</span><span class=\"mopen\">(</span><span class=\"mord mathnormal\">n</span><span class=\"mpunct\">;</span><span class=\"mspace\" style=\"margin-right:0.1667em;\"></span><span class=\"mord mathnormal\">p</span><span class=\"mclose\">)</span></span></span></span></span>.</p>\n<p>Alors il existe <span class=\"math-rendered\" data-latex=\"n\" data-latex-display=\"false\"><span class=\"katex\"><span class=\"katex-html\" aria-hidden=\"true\"><span class=\"base\"><span class=\"strut\" style=\"height:0.4306em;\"></span><span class=\"mord mathnormal\">n</span></span></span></span></span> variables aléatoires\nindépendantes <span class=\"math-rendered\" data-latex=\"X_1\" data-latex-display=\"false\"><span class=\"katex\"><span class=\"katex-html\" aria-hidden=\"true\"><span class=\"base\"><span class=\"strut\" style=\"height:0.8333em;vertical-align:-0.15em;\"></span><span class=\"mord\"><span class=\"mord mathnormal\" style=\"margin-right:0.07847em;\">X</span><span class=\"msupsub\"><span class=\"vlist-t vlist-t2\"><span class=\"vlist-r\"><span class=\"vlist\" style=\"height:0.3011em;\"><span style=\"top:-2.55em;margin-left:-0.0785em;margin-right:0.05em;\"><span class=\"pstrut\" style=\"height:2.7em;\"></span><span class=\"sizing reset-size6 size3 mtight\"><span class=\"mord mtight\">1</span></span></span></span><span class=\"vlist-s\">​</span></span><span class=\"vlist-r\"><span class=\"vlist\" style=\"height:0.15em;\"><span></span></span></span></span></span></span></span></span></span></span>, <span class=\"math-rendered\" data-latex=\"X_2\" data-latex-display=\"false\"><span class=\"katex\"><span class=\"katex-html\" aria-hidden=\"true\"><span class=\"base\"><span class=\"strut\" style=\"height:0.8333em;vertical-align:-0.15em;\"></span><span class=\"mord\"><span class=\"mord mathnormal\" style=\"margin-right:0.07847em;\">X</span><span class=\"msupsub\"><span class=\"vlist-t vlist-t2\"><span class=\"vlist-r\"><span class=\"vlist\" style=\"height:0.3011em;\"><span style=\"top:-2.55em;margin-left:-0.0785em;margin-right:0.05em;\"><span class=\"pstrut\" style=\"height:2.7em;\"></span><span class=\"sizing reset-size6 size3 mtight\"><span class=\"mord mtight\">2</span></span></span></span><span class=\"vlist-s\">​</span></span><span class=\"vlist-r\"><span class=\"vlist\" style=\"height:0.15em;\"><span></span></span></span></span></span></span></span></span></span></span>, ... ,\n<span class=\"math-rendered\" data-latex=\"X_n\" data-latex-display=\"false\"><span class=\"katex\"><span class=\"katex-html\" aria-hidden=\"true\"><span class=\"base\"><span class=\"strut\" style=\"height:0.8333em;vertical-align:-0.15em;\"></span><span class=\"mord\"><span class=\"mord mathnormal\" style=\"margin-right:0.07847em;\">X</span><span class=\"msupsub\"><span class=\"vlist-t vlist-t2\"><span class=\"vlist-r\"><span class=\"vlist\" style=\"height:0.1514em;\"><span style=\"top:-2.55em;margin-left:-0.0785em;margin-right:0.05em;\"><span class=\"pstrut\" style=\"height:2.7em;\"></span><span class=\"sizing reset-size6 size3 mtight\"><span class=\"mord mathnormal mtight\">n</span></span></span></span><span class=\"vlist-s\">​</span></span><span class=\"vlist-r\"><span class=\"vlist\" style=\"height:0.15em;\"><span></span></span></span></span></span></span></span></span></span></span> suivant toutes une loi de Bernoulli <span class=\"math-rendered\" data-latex=\"\\mathcal{B}(p)\" data-latex-display=\"false\"><span class=\"katex\"><span class=\"katex-html\" aria-hidden=\"true\"><span class=\"base\"><span class=\"strut\" style=\"height:1em;vertical-align:-0.25em;\"></span><span class=\"mord mathcal\" style=\"margin-right:0.03041em;\">B</span><span class=\"mopen\">(</span><span class=\"mord mathnormal\">p</span><span class=\"mclose\">)</span></span></span></span></span>, et telles que <span class=\"math-rendered\" data-latex=\"X = X_1 + X_2 + \\dots + X_n\" data-latex-display=\"false\"><span class=\"katex\"><span class=\"katex-html\" aria-hidden=\"true\"><span class=\"base\"><span class=\"strut\" style=\"height:0.6833em;\"></span><span class=\"mord mathnormal\" style=\"margin-right:0.07847em;\">X</span><span class=\"mspace\" style=\"margin-right:0.2778em;\"></span><span class=\"mrel\">=</span><span class=\"mspace\" style=\"margin-right:0.2778em;\"></span></span><span class=\"base\"><span class=\"strut\" style=\"height:0.8333em;vertical-align:-0.15em;\"></span><span class=\"mord\"><span class=\"mord mathnormal\" style=\"margin-right:0.07847em;\">X</span><span class=\"msupsub\"><span class=\"vlist-t vlist-t2\"><span class=\"vlist-r\"><span class=\"vlist\" style=\"height:0.3011em;\"><span style=\"top:-2.55em;margin-left:-0.0785em;margin-right:0.05em;\"><span class=\"pstrut\" style=\"height:2.7em;\"></span><span class=\"sizing reset-size6 size3 mtight\"><span class=\"mord mtight\">1</span></span></span></span><span class=\"vlist-s\">​</span></span><span class=\"vlist-r\"><span class=\"vlist\" style=\"height:0.15em;\"><span></span></span></span></span></span></span><span class=\"mspace\" style=\"margin-right:0.2222em;\"></span><span class=\"mbin\">+</span><span class=\"mspace\" style=\"margin-right:0.2222em;\"></span></span><span class=\"base\"><span class=\"strut\" style=\"height:0.8333em;vertical-align:-0.15em;\"></span><span class=\"mord\"><span class=\"mord mathnormal\" style=\"margin-right:0.07847em;\">X</span><span class=\"msupsub\"><span class=\"vlist-t vlist-t2\"><span class=\"vlist-r\"><span class=\"vlist\" style=\"height:0.3011em;\"><span style=\"top:-2.55em;margin-left:-0.0785em;margin-right:0.05em;\"><span class=\"pstrut\" style=\"height:2.7em;\"></span><span class=\"sizing reset-size6 size3 mtight\"><span class=\"mord mtight\">2</span></span></span></span><span class=\"vlist-s\">​</span></span><span class=\"vlist-r\"><span class=\"vlist\" style=\"height:0.15em;\"><span></span></span></span></span></span></span><span class=\"mspace\" style=\"margin-right:0.2222em;\"></span><span class=\"mbin\">+</span><span class=\"mspace\" style=\"margin-right:0.2222em;\"></span></span><span class=\"base\"><span class=\"strut\" style=\"height:0.6667em;vertical-align:-0.0833em;\"></span><span class=\"minner\">⋯</span><span class=\"mspace\" style=\"margin-right:0.2222em;\"></span><span class=\"mbin\">+</span><span class=\"mspace\" style=\"margin-right:0.2222em;\"></span></span><span class=\"base\"><span class=\"strut\" style=\"height:0.8333em;vertical-align:-0.15em;\"></span><span class=\"mord\"><span class=\"mord mathnormal\" style=\"margin-right:0.07847em;\">X</span><span class=\"msupsub\"><span class=\"vlist-t vlist-t2\"><span class=\"vlist-r\"><span class=\"vlist\" style=\"height:0.1514em;\"><span style=\"top:-2.55em;margin-left:-0.0785em;margin-right:0.05em;\"><span class=\"pstrut\" style=\"height:2.7em;\"></span><span class=\"sizing reset-size6 size3 mtight\"><span class=\"mord mathnormal mtight\">n</span></span></span></span><span class=\"vlist-s\">​</span></span><span class=\"vlist-r\"><span class=\"vlist\" style=\"height:0.15em;\"><span></span></span></span></span></span></span></span></span></span></span>.</p>\n</div>\n\n<h2 id=\"concentration-et-loi-des-grands-nombres\">Concentration et loi des grands nombres</h2>\n<h3 id=\"inegalite-de-bienayme-tchebychev\">Inégalité de Bienaymé-Tchebychev</h3>\n<div id=\"formula-8\" class=\"bubble\" data-variant=\"formula\">\n<h4>Inégalité de Bienaymé-Tchebychev</h4>\n<p>Soit <span class=\"math-rendered\" data-latex=\"X\" data-latex-display=\"false\"><span class=\"katex\"><span class=\"katex-html\" aria-hidden=\"true\"><span class=\"base\"><span class=\"strut\" style=\"height:0.6833em;\"></span><span class=\"mord mathnormal\" style=\"margin-right:0.07847em;\">X</span></span></span></span></span> une variable aléatoire d’espérance <span class=\"math-rendered\" data-latex=\"E(X) = \\mu\" data-latex-display=\"false\"><span class=\"katex\"><span class=\"katex-html\" aria-hidden=\"true\"><span class=\"base\"><span class=\"strut\" style=\"height:1em;vertical-align:-0.25em;\"></span><span class=\"mord mathnormal\" style=\"margin-right:0.05764em;\">E</span><span class=\"mopen\">(</span><span class=\"mord mathnormal\" style=\"margin-right:0.07847em;\">X</span><span class=\"mclose\">)</span><span class=\"mspace\" style=\"margin-right:0.2778em;\"></span><span class=\"mrel\">=</span><span class=\"mspace\" style=\"margin-right:0.2778em;\"></span></span><span class=\"base\"><span class=\"strut\" style=\"height:0.625em;vertical-align:-0.1944em;\"></span><span class=\"mord mathnormal\">μ</span></span></span></span></span> et de variance <span class=\"math-rendered\" data-latex=\"V(X) = V\" data-latex-display=\"false\"><span class=\"katex\"><span class=\"katex-html\" aria-hidden=\"true\"><span class=\"base\"><span class=\"strut\" style=\"height:1em;vertical-align:-0.25em;\"></span><span class=\"mord mathnormal\" style=\"margin-right:0.22222em;\">V</span><span class=\"mopen\">(</span><span class=\"mord mathnormal\" style=\"margin-right:0.07847em;\">X</span><span class=\"mclose\">)</span><span class=\"mspace\" style=\"margin-right:0.2778em;\"></span><span class=\"mrel\">=</span><span class=\"mspace\" style=\"margin-right:0.2778em;\"></span></span><span class=\"base\"><span class=\"strut\" style=\"height:0.6833em;\"></span><span class=\"mord mathnormal\" style=\"margin-right:0.22222em;\">V</span></span></span></span></span>.\nAlors pour tout réel strictement positif <span class=\"math-rendered\" data-latex=\"\\delta\" data-latex-display=\"false\"><span class=\"katex\"><span class=\"katex-html\" aria-hidden=\"true\"><span class=\"base\"><span class=\"strut\" style=\"height:0.6944em;\"></span><span class=\"mord mathnormal\" style=\"margin-right:0.03785em;\">δ</span></span></span></span></span>, <span class=\"math-rendered\" data-latex=\"P(|X-\\mu| \\geq \\delta) \\leq \\frac{V}{\\delta^2}\" data-latex-display=\"false\"><span class=\"katex\"><span class=\"katex-html\" aria-hidden=\"true\"><span class=\"base\"><span class=\"strut\" style=\"height:1em;vertical-align:-0.25em;\"></span><span class=\"mord mathnormal\" style=\"margin-right:0.13889em;\">P</span><span class=\"mopen\">(</span><span class=\"mord\">∣</span><span class=\"mord mathnormal\" style=\"margin-right:0.07847em;\">X</span><span class=\"mspace\" style=\"margin-right:0.2222em;\"></span><span class=\"mbin\">−</span><span class=\"mspace\" style=\"margin-right:0.2222em;\"></span></span><span class=\"base\"><span class=\"strut\" style=\"height:1em;vertical-align:-0.25em;\"></span><span class=\"mord mathnormal\">μ</span><span class=\"mord\">∣</span><span class=\"mspace\" style=\"margin-right:0.2778em;\"></span><span class=\"mrel\">≥</span><span class=\"mspace\" style=\"margin-right:0.2778em;\"></span></span><span class=\"base\"><span class=\"strut\" style=\"height:1em;vertical-align:-0.25em;\"></span><span class=\"mord mathnormal\" style=\"margin-right:0.03785em;\">δ</span><span class=\"mclose\">)</span><span class=\"mspace\" style=\"margin-right:0.2778em;\"></span><span class=\"mrel\">≤</span><span class=\"mspace\" style=\"margin-right:0.2778em;\"></span></span><span class=\"base\"><span class=\"strut\" style=\"height:1.2173em;vertical-align:-0.345em;\"></span><span class=\"mord\"><span class=\"mopen nulldelimiter\"></span><span class=\"mfrac\"><span class=\"vlist-t vlist-t2\"><span class=\"vlist-r\"><span class=\"vlist\" style=\"height:0.8723em;\"><span style=\"top:-2.655em;\"><span class=\"pstrut\" style=\"height:3em;\"></span><span class=\"sizing reset-size6 size3 mtight\"><span class=\"mord mtight\"><span class=\"mord mtight\"><span class=\"mord mathnormal mtight\" style=\"margin-right:0.03785em;\">δ</span><span class=\"msupsub\"><span class=\"vlist-t\"><span class=\"vlist-r\"><span class=\"vlist\" style=\"height:0.7463em;\"><span style=\"top:-2.786em;margin-right:0.0714em;\"><span class=\"pstrut\" style=\"height:2.5em;\"></span><span class=\"sizing reset-size3 size1 mtight\"><span class=\"mord mtight\">2</span></span></span></span></span></span></span></span></span></span></span><span style=\"top:-3.23em;\"><span class=\"pstrut\" style=\"height:3em;\"></span><span class=\"frac-line\" style=\"border-bottom-width:0.04em;\"></span></span><span style=\"top:-3.394em;\"><span class=\"pstrut\" style=\"height:3em;\"></span><span class=\"sizing reset-size6 size3 mtight\"><span class=\"mord mtight\"><span class=\"mord mathnormal mtight\" style=\"margin-right:0.22222em;\">V</span></span></span></span></span><span class=\"vlist-s\">​</span></span><span class=\"vlist-r\"><span class=\"vlist\" style=\"height:0.345em;\"><span></span></span></span></span></span><span class=\"mclose nulldelimiter\"></span></span></span></span></span></span>.</p>\n</div>\n\n\n<h3 id=\"inegalite-de-concentration\">Inégalité de concentration</h3>\n<div id=\"formula-9\" class=\"bubble\" data-variant=\"formula\">\n<h4>Inégalité de concentration</h4>\n<p>Soit <span class=\"math-rendered\" data-latex=\"(X_1, X_2, \\dots, X_n)\" data-latex-display=\"false\"><span class=\"katex\"><span class=\"katex-html\" aria-hidden=\"true\"><span class=\"base\"><span class=\"strut\" style=\"height:1em;vertical-align:-0.25em;\"></span><span class=\"mopen\">(</span><span class=\"mord\"><span class=\"mord mathnormal\" style=\"margin-right:0.07847em;\">X</span><span class=\"msupsub\"><span class=\"vlist-t vlist-t2\"><span class=\"vlist-r\"><span class=\"vlist\" style=\"height:0.3011em;\"><span style=\"top:-2.55em;margin-left:-0.0785em;margin-right:0.05em;\"><span class=\"pstrut\" style=\"height:2.7em;\"></span><span class=\"sizing reset-size6 size3 mtight\"><span class=\"mord mtight\">1</span></span></span></span><span class=\"vlist-s\">​</span></span><span class=\"vlist-r\"><span class=\"vlist\" style=\"height:0.15em;\"><span></span></span></span></span></span></span><span class=\"mpunct\">,</span><span class=\"mspace\" style=\"margin-right:0.1667em;\"></span><span class=\"mord\"><span class=\"mord mathnormal\" style=\"margin-right:0.07847em;\">X</span><span class=\"msupsub\"><span class=\"vlist-t vlist-t2\"><span class=\"vlist-r\"><span class=\"vlist\" style=\"height:0.3011em;\"><span style=\"top:-2.55em;margin-left:-0.0785em;margin-right:0.05em;\"><span class=\"pstrut\" style=\"height:2.7em;\"></span><span class=\"sizing reset-size6 size3 mtight\"><span class=\"mord mtight\">2</span></span></span></span><span class=\"vlist-s\">​</span></span><span class=\"vlist-r\"><span class=\"vlist\" style=\"height:0.15em;\"><span></span></span></span></span></span></span><span class=\"mpunct\">,</span><span class=\"mspace\" style=\"margin-right:0.1667em;\"></span><span class=\"minner\">…</span><span class=\"mspace\" style=\"margin-right:0.1667em;\"></span><span class=\"mpunct\">,</span><span class=\"mspace\" style=\"margin-right:0.1667em;\"></span><span class=\"mord\"><span class=\"mord mathnormal\" style=\"margin-right:0.07847em;\">X</span><span class=\"msupsub\"><span class=\"vlist-t vlist-t2\"><span class=\"vlist-r\"><span class=\"vlist\" style=\"height:0.1514em;\"><span style=\"top:-2.55em;margin-left:-0.0785em;margin-right:0.05em;\"><span class=\"pstrut\" style=\"height:2.7em;\"></span><span class=\"sizing reset-size6 size3 mtight\"><span class=\"mord mathnormal mtight\">n</span></span></span></span><span class=\"vlist-s\">​</span></span><span class=\"vlist-r\"><span class=\"vlist\" style=\"height:0.15em;\"><span></span></span></span></span></span></span><span class=\"mclose\">)</span></span></span></span></span> un échantillon\naléatoire de taille <span class=\"math-rendered\" data-latex=\"n\" data-latex-display=\"false\"><span class=\"katex\"><span class=\"katex-html\" aria-hidden=\"true\"><span class=\"base\"><span class=\"strut\" style=\"height:0.4306em;\"></span><span class=\"mord mathnormal\">n</span></span></span></span></span> associé à une loi d’espérance\n<span class=\"math-rendered\" data-latex=\"\\mu\" data-latex-display=\"false\"><span class=\"katex\"><span class=\"katex-html\" aria-hidden=\"true\"><span class=\"base\"><span class=\"strut\" style=\"height:0.625em;vertical-align:-0.1944em;\"></span><span class=\"mord mathnormal\">μ</span></span></span></span></span> et de variance <span class=\"math-rendered\" data-latex=\"V\" data-latex-display=\"false\"><span class=\"katex\"><span class=\"katex-html\" aria-hidden=\"true\"><span class=\"base\"><span class=\"strut\" style=\"height:0.6833em;\"></span><span class=\"mord mathnormal\" style=\"margin-right:0.22222em;\">V</span></span></span></span></span>. On pose\n<span class=\"math-rendered\" data-latex=\"M_n = \\frac{X_1 + X_2 + \\dots + X_n}{n}\" data-latex-display=\"false\"><span class=\"katex\"><span class=\"katex-html\" aria-hidden=\"true\"><span class=\"base\"><span class=\"strut\" style=\"height:0.8333em;vertical-align:-0.15em;\"></span><span class=\"mord\"><span class=\"mord mathnormal\" style=\"margin-right:0.10903em;\">M</span><span class=\"msupsub\"><span class=\"vlist-t vlist-t2\"><span class=\"vlist-r\"><span class=\"vlist\" style=\"height:0.1514em;\"><span style=\"top:-2.55em;margin-left:-0.109em;margin-right:0.05em;\"><span class=\"pstrut\" style=\"height:2.7em;\"></span><span class=\"sizing reset-size6 size3 mtight\"><span class=\"mord mathnormal mtight\">n</span></span></span></span><span class=\"vlist-s\">​</span></span><span class=\"vlist-r\"><span class=\"vlist\" style=\"height:0.15em;\"><span></span></span></span></span></span></span><span class=\"mspace\" style=\"margin-right:0.2778em;\"></span><span class=\"mrel\">=</span><span class=\"mspace\" style=\"margin-right:0.2778em;\"></span></span><span class=\"base\"><span class=\"strut\" style=\"height:1.2334em;vertical-align:-0.345em;\"></span><span class=\"mord\"><span class=\"mopen nulldelimiter\"></span><span class=\"mfrac\"><span class=\"vlist-t vlist-t2\"><span class=\"vlist-r\"><span class=\"vlist\" style=\"height:0.8884em;\"><span style=\"top:-2.655em;\"><span class=\"pstrut\" style=\"height:3em;\"></span><span class=\"sizing reset-size6 size3 mtight\"><span class=\"mord mtight\"><span class=\"mord mathnormal mtight\">n</span></span></span></span><span style=\"top:-3.23em;\"><span class=\"pstrut\" style=\"height:3em;\"></span><span class=\"frac-line\" style=\"border-bottom-width:0.04em;\"></span></span><span style=\"top:-3.4101em;\"><span class=\"pstrut\" style=\"height:3em;\"></span><span class=\"sizing reset-size6 size3 mtight\"><span class=\"mord mtight\"><span class=\"mord mtight\"><span class=\"mord mathnormal mtight\" style=\"margin-right:0.07847em;\">X</span><span class=\"msupsub\"><span class=\"vlist-t vlist-t2\"><span class=\"vlist-r\"><span class=\"vlist\" style=\"height:0.3173em;\"><span style=\"top:-2.357em;margin-left:-0.0785em;margin-right:0.0714em;\"><span class=\"pstrut\" style=\"height:2.5em;\"></span><span class=\"sizing reset-size3 size1 mtight\"><span class=\"mord mtight\">1</span></span></span></span><span class=\"vlist-s\">​</span></span><span class=\"vlist-r\"><span class=\"vlist\" style=\"height:0.143em;\"><span></span></span></span></span></span></span><span class=\"mbin mtight\">+</span><span class=\"mord mtight\"><span class=\"mord mathnormal mtight\" style=\"margin-right:0.07847em;\">X</span><span class=\"msupsub\"><span class=\"vlist-t vlist-t2\"><span class=\"vlist-r\"><span class=\"vlist\" style=\"height:0.3173em;\"><span style=\"top:-2.357em;margin-left:-0.0785em;margin-right:0.0714em;\"><span class=\"pstrut\" style=\"height:2.5em;\"></span><span class=\"sizing reset-size3 size1 mtight\"><span class=\"mord mtight\">2</span></span></span></span><span class=\"vlist-s\">​</span></span><span class=\"vlist-r\"><span class=\"vlist\" style=\"height:0.143em;\"><span></span></span></span></span></span></span><span class=\"mbin mtight\">+</span><span class=\"minner mtight\">⋯</span><span class=\"mbin mtight\">+</span><span class=\"mord mtight\"><span class=\"mord mathnormal mtight\" style=\"margin-right:0.07847em;\">X</span><span class=\"msupsub\"><span class=\"vlist-t vlist-t2\"><span class=\"vlist-r\"><span class=\"vlist\" style=\"height:0.1645em;\"><span style=\"top:-2.357em;margin-left:-0.0785em;margin-right:0.0714em;\"><span class=\"pstrut\" style=\"height:2.5em;\"></span><span class=\"sizing reset-size3 size1 mtight\"><span class=\"mord mathnormal mtight\">n</span></span></span></span><span class=\"vlist-s\">​</span></span><span class=\"vlist-r\"><span class=\"vlist\" style=\"height:0.143em;\"><span></span></span></span></span></span></span></span></span></span></span><span class=\"vlist-s\">​</span></span><span class=\"vlist-r\"><span class=\"vlist\" style=\"height:0.345em;\"><span></span></span></span></span></span><span class=\"mclose nulldelimiter\"></span></span></span></span></span></span>, la moyenne\nempirique de cet échantillon.</p>\n<p>Alors pour tout réel strictement positif <span class=\"math-rendered\" data-latex=\"\\delta\" data-latex-display=\"false\"><span class=\"katex\"><span class=\"katex-html\" aria-hidden=\"true\"><span class=\"base\"><span class=\"strut\" style=\"height:0.6944em;\"></span><span class=\"mord mathnormal\" style=\"margin-right:0.03785em;\">δ</span></span></span></span></span>,\n<span class=\"math-rendered\" data-latex=\"P(|M_n - \\mu| \\geq \\delta) \\leq \\frac{V}{n \\delta^2}\" data-latex-display=\"false\"><span class=\"katex\"><span class=\"katex-html\" aria-hidden=\"true\"><span class=\"base\"><span class=\"strut\" style=\"height:1em;vertical-align:-0.25em;\"></span><span class=\"mord mathnormal\" style=\"margin-right:0.13889em;\">P</span><span class=\"mopen\">(</span><span class=\"mord\">∣</span><span class=\"mord\"><span class=\"mord mathnormal\" style=\"margin-right:0.10903em;\">M</span><span class=\"msupsub\"><span class=\"vlist-t vlist-t2\"><span class=\"vlist-r\"><span class=\"vlist\" style=\"height:0.1514em;\"><span style=\"top:-2.55em;margin-left:-0.109em;margin-right:0.05em;\"><span class=\"pstrut\" style=\"height:2.7em;\"></span><span class=\"sizing reset-size6 size3 mtight\"><span class=\"mord mathnormal mtight\">n</span></span></span></span><span class=\"vlist-s\">​</span></span><span class=\"vlist-r\"><span class=\"vlist\" style=\"height:0.15em;\"><span></span></span></span></span></span></span><span class=\"mspace\" style=\"margin-right:0.2222em;\"></span><span class=\"mbin\">−</span><span class=\"mspace\" style=\"margin-right:0.2222em;\"></span></span><span class=\"base\"><span class=\"strut\" style=\"height:1em;vertical-align:-0.25em;\"></span><span class=\"mord mathnormal\">μ</span><span class=\"mord\">∣</span><span class=\"mspace\" style=\"margin-right:0.2778em;\"></span><span class=\"mrel\">≥</span><span class=\"mspace\" style=\"margin-right:0.2778em;\"></span></span><span class=\"base\"><span class=\"strut\" style=\"height:1em;vertical-align:-0.25em;\"></span><span class=\"mord mathnormal\" style=\"margin-right:0.03785em;\">δ</span><span class=\"mclose\">)</span><span class=\"mspace\" style=\"margin-right:0.2778em;\"></span><span class=\"mrel\">≤</span><span class=\"mspace\" style=\"margin-right:0.2778em;\"></span></span><span class=\"base\"><span class=\"strut\" style=\"height:1.2173em;vertical-align:-0.345em;\"></span><span class=\"mord\"><span class=\"mopen nulldelimiter\"></span><span class=\"mfrac\"><span class=\"vlist-t vlist-t2\"><span class=\"vlist-r\"><span class=\"vlist\" style=\"height:0.8723em;\"><span style=\"top:-2.655em;\"><span class=\"pstrut\" style=\"height:3em;\"></span><span class=\"sizing reset-size6 size3 mtight\"><span class=\"mord mtight\"><span class=\"mord mathnormal mtight\">n</span><span class=\"mord mtight\"><span class=\"mord mathnormal mtight\" style=\"margin-right:0.03785em;\">δ</span><span class=\"msupsub\"><span class=\"vlist-t\"><span class=\"vlist-r\"><span class=\"vlist\" style=\"height:0.7463em;\"><span style=\"top:-2.786em;margin-right:0.0714em;\"><span class=\"pstrut\" style=\"height:2.5em;\"></span><span class=\"sizing reset-size3 size1 mtight\"><span class=\"mord mtight\">2</span></span></span></span></span></span></span></span></span></span></span><span style=\"top:-3.23em;\"><span class=\"pstrut\" style=\"height:3em;\"></span><span class=\"frac-line\" style=\"border-bottom-width:0.04em;\"></span></span><span style=\"top:-3.394em;\"><span class=\"pstrut\" style=\"height:3em;\"></span><span class=\"sizing reset-size6 size3 mtight\"><span class=\"mord mtight\"><span class=\"mord mathnormal mtight\" style=\"margin-right:0.22222em;\">V</span></span></span></span></span><span class=\"vlist-s\">​</span></span><span class=\"vlist-r\"><span class=\"vlist\" style=\"height:0.345em;\"><span></span></span></span></span></span><span class=\"mclose nulldelimiter\"></span></span></span></span></span></span>.</p>\n</div>\n<h3 id=\"loi-des-grands-nombres\">Loi des grands nombres</h3>\n<div id=\"formula-10\" class=\"bubble\" data-variant=\"formula\">\n<h4>Loi faible des grands nombres</h4>\n<p>Soit <span class=\"math-rendered\" data-latex=\"(X_1, X_2, \\dots, X_n)\" data-latex-display=\"false\"><span class=\"katex\"><span class=\"katex-html\" aria-hidden=\"true\"><span class=\"base\"><span class=\"strut\" style=\"height:1em;vertical-align:-0.25em;\"></span><span class=\"mopen\">(</span><span class=\"mord\"><span class=\"mord mathnormal\" style=\"margin-right:0.07847em;\">X</span><span class=\"msupsub\"><span class=\"vlist-t vlist-t2\"><span class=\"vlist-r\"><span class=\"vlist\" style=\"height:0.3011em;\"><span style=\"top:-2.55em;margin-left:-0.0785em;margin-right:0.05em;\"><span class=\"pstrut\" style=\"height:2.7em;\"></span><span class=\"sizing reset-size6 size3 mtight\"><span class=\"mord mtight\">1</span></span></span></span><span class=\"vlist-s\">​</span></span><span class=\"vlist-r\"><span class=\"vlist\" style=\"height:0.15em;\"><span></span></span></span></span></span></span><span class=\"mpunct\">,</span><span class=\"mspace\" style=\"margin-right:0.1667em;\"></span><span class=\"mord\"><span class=\"mord mathnormal\" style=\"margin-right:0.07847em;\">X</span><span class=\"msupsub\"><span class=\"vlist-t vlist-t2\"><span class=\"vlist-r\"><span class=\"vlist\" style=\"height:0.3011em;\"><span style=\"top:-2.55em;margin-left:-0.0785em;margin-right:0.05em;\"><span class=\"pstrut\" style=\"height:2.7em;\"></span><span class=\"sizing reset-size6 size3 mtight\"><span class=\"mord mtight\">2</span></span></span></span><span class=\"vlist-s\">​</span></span><span class=\"vlist-r\"><span class=\"vlist\" style=\"height:0.15em;\"><span></span></span></span></span></span></span><span class=\"mpunct\">,</span><span class=\"mspace\" style=\"margin-right:0.1667em;\"></span><span class=\"minner\">…</span><span class=\"mspace\" style=\"margin-right:0.1667em;\"></span><span class=\"mpunct\">,</span><span class=\"mspace\" style=\"margin-right:0.1667em;\"></span><span class=\"mord\"><span class=\"mord mathnormal\" style=\"margin-right:0.07847em;\">X</span><span class=\"msupsub\"><span class=\"vlist-t vlist-t2\"><span class=\"vlist-r\"><span class=\"vlist\" style=\"height:0.1514em;\"><span style=\"top:-2.55em;margin-left:-0.0785em;margin-right:0.05em;\"><span class=\"pstrut\" style=\"height:2.7em;\"></span><span class=\"sizing reset-size6 size3 mtight\"><span class=\"mord mathnormal mtight\">n</span></span></span></span><span class=\"vlist-s\">​</span></span><span class=\"vlist-r\"><span class=\"vlist\" style=\"height:0.15em;\"><span></span></span></span></span></span></span><span class=\"mclose\">)</span></span></span></span></span> un échantillon\naléatoire de taille <span class=\"math-rendered\" data-latex=\"n\" data-latex-display=\"false\"><span class=\"katex\"><span class=\"katex-html\" aria-hidden=\"true\"><span class=\"base\"><span class=\"strut\" style=\"height:0.4306em;\"></span><span class=\"mord mathnormal\">n</span></span></span></span></span> associé à une loi d’espérance\n<span class=\"math-rendered\" data-latex=\"\\mu\" data-latex-display=\"false\"><span class=\"katex\"><span class=\"katex-html\" aria-hidden=\"true\"><span class=\"base\"><span class=\"strut\" style=\"height:0.625em;vertical-align:-0.1944em;\"></span><span class=\"mord mathnormal\">μ</span></span></span></span></span> et de variance <span class=\"math-rendered\" data-latex=\"V\" data-latex-display=\"false\"><span class=\"katex\"><span class=\"katex-html\" aria-hidden=\"true\"><span class=\"base\"><span class=\"strut\" style=\"height:0.6833em;\"></span><span class=\"mord mathnormal\" style=\"margin-right:0.22222em;\">V</span></span></span></span></span>. On pose\n<span class=\"math-rendered\" data-latex=\"M_n = \\frac{X_1 + X_2 + \\dots + X_n}{n}\" data-latex-display=\"false\"><span class=\"katex\"><span class=\"katex-html\" aria-hidden=\"true\"><span class=\"base\"><span class=\"strut\" style=\"height:0.8333em;vertical-align:-0.15em;\"></span><span class=\"mord\"><span class=\"mord mathnormal\" style=\"margin-right:0.10903em;\">M</span><span class=\"msupsub\"><span class=\"vlist-t vlist-t2\"><span class=\"vlist-r\"><span class=\"vlist\" style=\"height:0.1514em;\"><span style=\"top:-2.55em;margin-left:-0.109em;margin-right:0.05em;\"><span class=\"pstrut\" style=\"height:2.7em;\"></span><span class=\"sizing reset-size6 size3 mtight\"><span class=\"mord mathnormal mtight\">n</span></span></span></span><span class=\"vlist-s\">​</span></span><span class=\"vlist-r\"><span class=\"vlist\" style=\"height:0.15em;\"><span></span></span></span></span></span></span><span class=\"mspace\" style=\"margin-right:0.2778em;\"></span><span class=\"mrel\">=</span><span class=\"mspace\" style=\"margin-right:0.2778em;\"></span></span><span class=\"base\"><span class=\"strut\" style=\"height:1.2334em;vertical-align:-0.345em;\"></span><span class=\"mord\"><span class=\"mopen nulldelimiter\"></span><span class=\"mfrac\"><span class=\"vlist-t vlist-t2\"><span class=\"vlist-r\"><span class=\"vlist\" style=\"height:0.8884em;\"><span style=\"top:-2.655em;\"><span class=\"pstrut\" style=\"height:3em;\"></span><span class=\"sizing reset-size6 size3 mtight\"><span class=\"mord mtight\"><span class=\"mord mathnormal mtight\">n</span></span></span></span><span style=\"top:-3.23em;\"><span class=\"pstrut\" style=\"height:3em;\"></span><span class=\"frac-line\" style=\"border-bottom-width:0.04em;\"></span></span><span style=\"top:-3.4101em;\"><span class=\"pstrut\" style=\"height:3em;\"></span><span class=\"sizing reset-size6 size3 mtight\"><span class=\"mord mtight\"><span class=\"mord mtight\"><span class=\"mord mathnormal mtight\" style=\"margin-right:0.07847em;\">X</span><span class=\"msupsub\"><span class=\"vlist-t vlist-t2\"><span class=\"vlist-r\"><span class=\"vlist\" style=\"height:0.3173em;\"><span style=\"top:-2.357em;margin-left:-0.0785em;margin-right:0.0714em;\"><span class=\"pstrut\" style=\"height:2.5em;\"></span><span class=\"sizing reset-size3 size1 mtight\"><span class=\"mord mtight\">1</span></span></span></span><span class=\"vlist-s\">​</span></span><span class=\"vlist-r\"><span class=\"vlist\" style=\"height:0.143em;\"><span></span></span></span></span></span></span><span class=\"mbin mtight\">+</span><span class=\"mord mtight\"><span class=\"mord mathnormal mtight\" style=\"margin-right:0.07847em;\">X</span><span class=\"msupsub\"><span class=\"vlist-t vlist-t2\"><span class=\"vlist-r\"><span class=\"vlist\" style=\"height:0.3173em;\"><span style=\"top:-2.357em;margin-left:-0.0785em;margin-right:0.0714em;\"><span class=\"pstrut\" style=\"height:2.5em;\"></span><span class=\"sizing reset-size3 size1 mtight\"><span class=\"mord mtight\">2</span></span></span></span><span class=\"vlist-s\">​</span></span><span class=\"vlist-r\"><span class=\"vlist\" style=\"height:0.143em;\"><span></span></span></span></span></span></span><span class=\"mbin mtight\">+</span><span class=\"minner mtight\">⋯</span><span class=\"mbin mtight\">+</span><span class=\"mord mtight\"><span class=\"mord mathnormal mtight\" style=\"margin-right:0.07847em;\">X</span><span class=\"msupsub\"><span class=\"vlist-t vlist-t2\"><span class=\"vlist-r\"><span class=\"vlist\" style=\"height:0.1645em;\"><span style=\"top:-2.357em;margin-left:-0.0785em;margin-right:0.0714em;\"><span class=\"pstrut\" style=\"height:2.5em;\"></span><span class=\"sizing reset-size3 size1 mtight\"><span class=\"mord mathnormal mtight\">n</span></span></span></span><span class=\"vlist-s\">​</span></span><span class=\"vlist-r\"><span class=\"vlist\" style=\"height:0.143em;\"><span></span></span></span></span></span></span></span></span></span></span><span class=\"vlist-s\">​</span></span><span class=\"vlist-r\"><span class=\"vlist\" style=\"height:0.345em;\"><span></span></span></span></span></span><span class=\"mclose nulldelimiter\"></span></span></span></span></span></span>, la moyenne\nempirique de cet échantillon.</p>\n<p>Alors pour tout réel strictement positif <span class=\"math-rendered\" data-latex=\"\\delta\" data-latex-display=\"false\"><span class=\"katex\"><span class=\"katex-html\" aria-hidden=\"true\"><span class=\"base\"><span class=\"strut\" style=\"height:0.6944em;\"></span><span class=\"mord mathnormal\" style=\"margin-right:0.03785em;\">δ</span></span></span></span></span>,\n<span class=\"math-rendered\" data-latex=\"\\lim\\limits_{n \\rightarrow +\\infty} P(|M_n - \\mu| \\geq \\delta) = 0\" data-latex-display=\"false\"><span class=\"katex\"><span class=\"katex-html\" aria-hidden=\"true\"><span class=\"base\"><span class=\"strut\" style=\"height:1.5083em;vertical-align:-0.7583em;\"></span><span class=\"mop op-limits\"><span class=\"vlist-t vlist-t2\"><span class=\"vlist-r\"><span class=\"vlist\" style=\"height:0.6944em;\"><span style=\"top:-2.4em;margin-left:0em;\"><span class=\"pstrut\" style=\"height:3em;\"></span><span class=\"sizing reset-size6 size3 mtight\"><span class=\"mord mtight\"><span class=\"mord mathnormal mtight\">n</span><span class=\"mrel mtight\">→</span><span class=\"mord mtight\">+</span><span class=\"mord mtight\">∞</span></span></span></span><span style=\"top:-3em;\"><span class=\"pstrut\" style=\"height:3em;\"></span><span><span class=\"mop\">lim</span></span></span></span><span class=\"vlist-s\">​</span></span><span class=\"vlist-r\"><span class=\"vlist\" style=\"height:0.7583em;\"><span></span></span></span></span></span><span class=\"mspace\" style=\"margin-right:0.1667em;\"></span><span class=\"mord mathnormal\" style=\"margin-right:0.13889em;\">P</span><span class=\"mopen\">(</span><span class=\"mord\">∣</span><span class=\"mord\"><span class=\"mord mathnormal\" style=\"margin-right:0.10903em;\">M</span><span class=\"msupsub\"><span class=\"vlist-t vlist-t2\"><span class=\"vlist-r\"><span class=\"vlist\" style=\"height:0.1514em;\"><span style=\"top:-2.55em;margin-left:-0.109em;margin-right:0.05em;\"><span class=\"pstrut\" style=\"height:2.7em;\"></span><span class=\"sizing reset-size6 size3 mtight\"><span class=\"mord mathnormal mtight\">n</span></span></span></span><span class=\"vlist-s\">​</span></span><span class=\"vlist-r\"><span class=\"vlist\" style=\"height:0.15em;\"><span></span></span></span></span></span></span><span class=\"mspace\" style=\"margin-right:0.2222em;\"></span><span class=\"mbin\">−</span><span class=\"mspace\" style=\"margin-right:0.2222em;\"></span></span><span class=\"base\"><span class=\"strut\" style=\"height:1em;vertical-align:-0.25em;\"></span><span class=\"mord mathnormal\">μ</span><span class=\"mord\">∣</span><span class=\"mspace\" style=\"margin-right:0.2778em;\"></span><span class=\"mrel\">≥</span><span class=\"mspace\" style=\"margin-right:0.2778em;\"></span></span><span class=\"base\"><span class=\"strut\" style=\"height:1em;vertical-align:-0.25em;\"></span><span class=\"mord mathnormal\" style=\"margin-right:0.03785em;\">δ</span><span class=\"mclose\">)</span><span class=\"mspace\" style=\"margin-right:0.2778em;\"></span><span class=\"mrel\">=</span><span class=\"mspace\" style=\"margin-right:0.2778em;\"></span></span><span class=\"base\"><span class=\"strut\" style=\"height:0.6444em;\"></span><span class=\"mord\">0</span></span></span></span></span>.</p>\n</div>\n\n","level":"terminale","id":"variables-aleatoires-concentration-grands-nombres","title":"Variables aléatoires, concentration et loi des grands nombres","chapter":11,"caption":"Les variables aléatoires servent à décrire toutes sortes de phénomènes probabilistes.","description":"En mathématiques, la loi des grands nombres permet d’interpréter la probabilité comme une fréquence de réalisation, justifiant ainsi le principe des sondages, et présente l’espérance comme une moyenne. Nous commencerons ce chapitre par quelques rappels sur les variables aléatoires. Nous approfondirons cette notions en sommant plusieurs variables aléatoires, puis nous verrons certains résultats très importants en probabilités et en statistiques, comme l’inégalité de Bienaymé-Tchebychev, l’inégalité de concentration et la loi des grands nombres.","difficulty":5,"title-search":"variables aleatoires, concentration et loi des grands nombres (terminale)","pdf":"/pdf/terminale/variables-aleatoires-concentration-grands-nombres.pdf","preview":"/img/lessons/terminale/variables-aleatoires-concentration-grands-nombres/preview.jpg","toc":[{"id":"somme-de-deux-variables-aleatoires","text":"Somme de deux variables aléatoires","depth":2,"children":[{"id":"definition","text":"Définition","depth":3,"children":[]},{"id":"esperance-variance-et-ecart-type","text":"Espérance, variance et écart-type","depth":3,"children":[]}]},{"id":"somme-de-plusieurs-variables-aleatoires","text":"Somme de plusieurs variables aléatoires","depth":2,"children":[{"id":"definition-et-proprietes","text":"Définition et propriétés","depth":3,"children":[]},{"id":"somme--decompositions-de-certaines-variables-aleatoires","text":"Somme / décompositions de certaines variables aléatoires","depth":3,"children":[]}]},{"id":"concentration-et-loi-des-grands-nombres","text":"Concentration et loi des grands nombres","depth":2,"children":[{"id":"inegalite-de-bienayme-tchebychev","text":"Inégalité de Bienaymé-Tchebychev","depth":3,"children":[]},{"id":"inegalite-de-concentration","text":"Inégalité de concentration","depth":3,"children":[]},{"id":"loi-des-grands-nombres","text":"Loi des grands nombres","depth":3,"children":[]}]}],"_source":"content","_file":"latex/lessons/terminale/variables-aleatoires-concentration-grands-nombres.tex","_stem":"latex/lessons/terminale/variables-aleatoires-concentration-grands-nombres","_extension":"tex"}